Workbook

Sheet Сценарии и выводы
C2: CYBERBARA · Экономическое обоснование
C4: Сценарий: | D4: ='Исходные данные'!$G$5 -> Базовый
C6: Основной результат | D6: Значение | E6: Единица
C7: Цена подписки | D7: ='Исходные данные'!$D$33 -> 20000 | E7: руб./мес.
C8: Цена внедрения | D8: ='Исходные данные'!$D$37 -> 50000 | E8: руб./клиент
C9: Стоимость создания MVP | D9: ='CAPEX OPEX TCO'!D11 -> 2424769.2 | E9: руб.
C10: Деньги на разработку без выплат команде | D10: ='CAPEX OPEX TCO'!D12 -> 90000 | E10: руб.
C11: Целевой пул компенсации | D11: ='COCOMO и разработка'!G43 -> 2307097.2 | E11: руб.
C12: Пиковая потребность в финансировании | D12: ='NPV IRR окупаемость'!E14 -> 206732.51 | E12: руб.
C13: NPV с учётом стоимости труда | D13: ='NPV IRR окупаемость'!D10 -> 5920462.3 | E13: руб.
C14: Годовая IRR с учётом стоимости труда | D14: ='NPV IRR окупаемость'!D12 -> 1.4420596 | E14: доля
C15: Дисконтированная окупаемость | D15: ='NPV IRR окупаемость'!D13 -> 21.694465 | E15: месяцы
C16: Выплачено команде за 36 месяцев | D16: =SUM('Продажи и потоки'!D39:AN39) -> 2307097.2 | E16: руб.
C17: Осталось компенсировать | D17: ='NPV IRR окупаемость'!E16 -> 0 | E17: руб.
C18: Месяц полного возврата команде | D18: ='NPV IRR окупаемость'!E15 -> 25 | E18: месяц
C19: Активные клиенты в месяце 36 | D19: ='Продажи и потоки'!AN16 -> 75.382181 | E19: ожидаемое число
C20: Безубыточность подписки на старте | D20: ='Тарифы и юнит-экономика'!D21 -> 7 | E20: клиенты
C21: Ценовой ориентир с возвратом труда | D21: ='Тарифы и юнит-экономика'!D33 -> 13566.179 | E21: руб./мес.
C24: Экономическая целесообразность | D24: =IF('NPV IRR окупаемость'!D10>0,"Положительная в выбранном сценарии","Не подтверждена в выбранном сценарии") -> Положительная в выбранном сценарии
C25: Согласованность срока MVP | D25: ='COCOMO и разработка'!D48 -> Ёмкость достаточна
C28: Как проверить сценарии: на листе «Исходные данные» измените D5: 1 — база, 2 — риск, 3 — рост. Все результаты и графики пересчитаются.
C30: Это прогноз на учебных допущениях, а не доказательство спроса. Тарифы 20 000 / 50 000 ₽ и возврат 50% согласованы пользователем.
C32: Компенсация выплачивается только после покрытия текущих расходов и накопленного кассового дефицита, до исчерпания пула.
C34: Экономическая окупаемость и возврат денег команде — разные показатели. Стоимость труда включена один раз, а не и как инвестиция, и повторно как расход.
C36: Налоговая модель упрощена: условная ставка с выручки, НДС по календарным порогам, без льгот, вычетов и квартального графика платежей.
C40: Сценарий | D40: Подписка | E40: Отток / мес. | F40: Темп продаж | G40: Ставка DR
C41: Базовый | D41: ='Исходные данные'!D34 -> 20000 | E41: ='Исходные данные'!D42 -> 0.02 | F41: ='Исходные данные'!D74 -> 1 | G41: ='Исходные данные'!D58 -> 0.25
C42: Пессимистичный | D42: ='Исходные данные'!D35 -> 18000 | E42: ='Исходные данные'!D43 -> 0.04 | F42: ='Исходные данные'!D75 -> 0.5 | G42: ='Исходные данные'!D59 -> 0.35
C43: Оптимистичный | D43: ='Исходные данные'!D36 -> 22000 | E43: ='Исходные данные'!D44 -> 0.01 | F43: ='Исходные данные'!D76 -> 1.5 | G43: ='Исходные данные'!D60 -> 0.2
C46: В таблице выше сравниваются вводные сценариев, не сохранённые финансовые результаты. Для каждого результата выберите соответствующий сценарий в D5.
C49: Обновление стоимости: 4 участника, рыночный ФОТ и обязательные взносы. Имеющиеся компьютеры оцениваются по реальным комплектующим; амортизация включена в ресурсную стоимость и минимальную цену, но не списывается повторно из кассы.

Sheet Исходные данные
C2: Исходные данные
C4: Сценарий: | D4: См. единственный переключатель D5 | E4: См. единственный переключатель D5 | F4: См. единственный переключатель D5 | G4: См. единственный переключатель D5
C5: Сценарий: 1 база, 2 риск, 3 рост | D5: 1 | G5: =CHOOSE(D5,"Базовый","Пессимистичный","Оптимистичный") -> Базовый
C8: Общий параметр | D8: Значение | E8: Единица | F8: Статус | H8: Источник / основание
C9: Начало расчёта | D9: 46327 | E9: дата | F9: Допущение | H9: Месяц 1 = ноябрь 2026; дата редактируется
C10: Разработка MVP | D10: 4 | E10: месяца | F10: Из практик 1, 3 | H10: 16 недель представлены четырьмя расчётными месяцами
C11: Участники команды | D11: 4 | E11: человека | F11: Практика 1 + реальность | H11: 4 автора; роли совмещаются, это не шесть отдельных сотрудников
C12: Доля свободного потока на компенсацию | D12: 0.5 | E12: доля | F12: Подтверждено | H12: Примерное распределение компенсации затрат
C13: Резерв налога с выручки без НДС | D13: 0.06 | E13: доля | F13: Допущение | H13: Учебное приближение УСН «доходы»; без уменьшения на взносы
C14: НДС после утраты освобождения | D14: 0.05 | E14: доля | F14: Допущение | H14: Модель ставки 5%, цена клиенту включает НДС; льготу ПО не предполагаем
C15: Страховые взносы работодателя в пределах годовой базы | D15: 0.3 | E15: доля | F15: Общий тариф, ФНС, 2026 | H15: 30% в пределах базы. Без льготы ИТ. https://www.nalog.gov.ru/rn77/news/activities_fts/16577139/
C16: Первоначальные денежные расходы | D16: 30000 | E16: руб. | F16: Допущение | H16: Разовая подготовка инфраструктуры и материалов; период 0
C17: Денежные расходы в месяц разработки | D17: 15000 | E17: руб./мес. | F17: Допущение | H17: Сервер разработки, данные и проверка качества; без оплаты команды
C18: Клиенты для расчёта ценового ориентира | D18: 30 | E18: организаций | F18: Допущение | H18: Не прогноз продаж; база распределения общих затрат
C19: Срок возврата труда в ценовом ориентире | D19: 24 | E19: месяца | F19: Допущение | H19: Не гарантированный срок фактической компенсации
C20: Предельный срок LTV для расчёта | D20: 24 | E20: месяца | F20: Допущение | H20: LTV ограничен сроком и оттоком, а не бесконечным удержанием
... C31: Страховые взносы сверх предельной годовой базы | D31: 0.151 | E31: доля | F31: Параметр 2026 | H31: ФНС, общий тариф 15,1%. https://www.nalog.gov.ru/rn77/news/activities_fts/16577139/
C32: Драйвер / вариант | D32: Значение | E32: Единица | F32: Статус | H32: Основание
C33: Активный: Подписка | D33: =IF(ISNUMBER(INDEX(D34:D36,$D$5)),INDEX(D34:D36,$D$5),NA()) -> 20000 | E33: руб./мес. | F33: Гипотеза | H33: База подтверждена пользователем; прочие варианты — допущения
C34: Базовый | D34: 20000
C35: Пессимистичный | D35: 18000
C36: Оптимистичный | D36: 22000
C37: Активный: Внедрение | D37: =IF(ISNUMBER(INDEX(D38:D40,$D$5)),INDEX(D38:D40,$D$5),NA()) -> 50000 | E37: руб./клиент | F37: Гипотеза | H37: База: практика 3 и ответ пользователя
C38: Базовый | D38: 50000
C39: Пессимистичный | D39: 40000
C40: Оптимистичный | D40: 60000
C41: Активный: Месячный отток | D41: =IF(ISNUMBER(INDEX(D42:D44,$D$5)),INDEX(D42:D44,$D$5),NA()) -> 0.02 | E41: доля | F41: Гипотеза | H41: Прогноз ожидаемых значений; нет фактической истории
C42: Базовый | D42: 0.02
C43: Пессимистичный | D43: 0.04
C44: Оптимистичный | D44: 0.01
C45: Активный: Переменные расходы | D45: =IF(ISNUMBER(INDEX(D46:D48,$D$5)),INDEX(D46:D48,$D$5),NA()) -> 5000 | E45: руб./клиент/мес. | F45: Гипотеза | H45: Вычисления, данные и поддержка; не включены в постоянные расходы
C46: Базовый | D46: 5000
C47: Пессимистичный | D47: 7000
C48: Оптимистичный | D48: 4000
C49: Активный: Себестоимость внедрения | D49: =IF(ISNUMBER(INDEX(D50:D52,$D$5)),INDEX(D50:D52,$D$5),NA()) -> 15000 | E49: руб./клиент | F49: Гипотеза | H49: Оплачиваемые работы после запуска, отдельно от стоимости MVP
C50: Базовый | D50: 15000
C51: Пессимистичный | D51: 20000
C52: Оптимистичный | D52: 12000
C53: Активный: Переменное привлечение | D53: =IF(ISNUMBER(INDEX(D54:D56,$D$5)),INDEX(D54:D56,$D$5),NA()) -> 15000 | E53: руб./новый клиент | F53: Гипотеза | H53: Дополнительно к постоянному маркетинговому бюджету
C54: Базовый | D54: 15000
C55: Пессимистичный | D55: 22000
C56: Оптимистичный | D56: 12000
C57: Активный: Годовая ставка дисконтирования | D57: =IF(ISNUMBER(INDEX(D58:D60,$D$5)),INDEX(D58:D60,$D$5),NA()) -> 0.25 | E57: доля | F57: Гипотеза | H57: Учебная требуемая доходность; не подмена актуальной ключевой ставки
C58: Базовый | D58: 0.25
C59: Пессимистичный | D59: 0.35
C60: Оптимистичный | D60: 0.2
C61: Активный: Объём собственного кода | D61: =IF(ISNUMBER(INDEX(D62:D64,$D$5)),INDEX(D62:D64,$D$5),NA()) -> 1.5 | E61: KSLOC | F61: Гипотеза | H61: Экспертная оценка MVP; библиотеки и сгенерированный код не включены
C62: Базовый | D62: 1.5
C63: Пессимистичный | D63: 1.9
C64: Оптимистичный | D64: 1.3
C65: Активный: Общие расходы после запуска | D65: =IF(ISNUMBER(INDEX(D66:D68,$D$5)),INDEX(D66:D68,$D$5),NA()) -> 80000 | E65: руб./мес. | F65: Гипотеза | H65: База: сопровождение 45 тыс., сервер 15 тыс., администрирование 10 тыс., маркетинг 10 тыс.
C66: Базовый | D66: 80000
C67: Пессимистичный | D67: 100000
C68: Оптимистичный | D68: 100000
C69: Активный: Ежегодный рост расходов | D69: =IF(ISNUMBER(INDEX(D70:D72,$D$5)),INDEX(D70:D72,$D$5),NA()) -> 0.05 | E69: доля | F69: Гипотеза | H69: Индексируем денежные расходы после запуска, цены подписки неизменны
C70: Базовый | D70: 0.05
C71: Пессимистичный | D71: 0.08
C72: Оптимистичный | D72: 0.05
C73: Активный: Изменение темпа продаж | D73: =IF(ISNUMBER(INDEX(D74:D76,$D$5)),INDEX(D74:D76,$D$5),NA()) -> 1 | E73: множитель | F73: Гипотеза | H73: Единый множитель базового помесячного плана
C74: Базовый | D74: 1
C75: Пессимистичный | D75: 0.5
C76: Оптимистичный | D76: 1.5
C79: Источник | D79: Использованные сведения | H79: Ссылка / документ
C80: Практика 1 | D80: Срок, команда, функциональные границы | H80: Практика_1.docx, SMART-цель и описание
C81: Практика 2 | D81: Риски поставщиков, стоимости ИИ и конкуренции | H81: Практика_2_PEST_5P.xlsx, PEST и 5PP
C82: Практика 3 | D82: MVP, подписка и плата за внедрение | H82: Практика_3.docx, концепция и MVP
C83: Лекция 4 | D83: Юнит-экономика, NPV, IRR, DPP | H83: Архитектура бизнеса… 1-8.pdf, стр. 59–76
C84: Пособие 4 | D84: COCOMO II, TCO, конкурентоспособность | H84: Пособие для практики №4 (разработка софта).pdf
C85: Задание 4 | D85: Excel, стоимость ПО, NPV, IRR, DPP, график | H85: Практическое занятие №4.pptx, слайд 4
C86: ФНС | D86: Условия НДС и снижение порогов | H86: https://www.nalog.gov.ru/new2026/
C87: Brand Analytics | D87: Ценовой ориентир и функции | H87: https://brandanalytics.ru/kz_RU/price/
C88: YouScan | D88: Ценовой ориентир и функции | H88: https://youscan.io/pricing/
C89: СКАН | D89: Описание возможностей; цена не опубликована | H89: https://scan-interfax.ru/
C90: Пользователь | D90: Тарифы и схема компенсации | H90: Примерная реализация
C92: Жёлтые ячейки с синим числом редактируются. Сценарии переключаются только в D5. Реальные продажи и расходы отсутствуют.
C94: Подписка и внедрение оплачиваются в том же месяце. НДС при превышении порога — с последующего месяца; льготы на ПО не заложены.
C96: Компенсация — управленческая оценка вклада команды с резервом оформления. Она не означает оформленную задолженность по зарплате.
D98: 0 | E98: 1 | F98: 2 | G98: 3 | H98: 4 | I98: 5 | J98: 6 | K98: 7 | L98: 8 | M98: 9 | N98: 10 | O98: 11 | P98: 12 | Q98: 13 | R98: 14 | S98: 15 | T98: 16 | U98: 17 | V98: 18 | W98: 19 | X98: 20 | Y98: 21 | Z98: 22 | AA98: 23 | AB98: 24 | AC98: 25 | AD98: 26 | AE98: 27 | AF98: 28 | AG98: 29 | AH98: 30 | AI98: 31 | AJ98: 32 | AK98: 33 | AL98: 34 | AM98: 35 | AN98: 36
C99: План новых клиентов / месяц
C100: Базовый темп продаж | D100: 0 | E100: 0 | F100: 0 | G100: 0 | H100: 0 | I100: 1 | J100: 1 | K100: 1 | L100: 1 | M100: 2 | N100: 2 | O100: 2 | P100: 2 | Q100: 3 | R100: 3 | S100: 3 | T100: 3 | U100: 3 | V100: 3 | W100: 3 | X100: 3 | Y100: 3 | Z100: 3 | AA100: 3 | AB100: 3 | AC100: 4 | AD100: 4 | AE100: 4 | AF100: 4 | AG100: 4 | AH100: 4 | AI100: 4 | AJ100: 4 | AK100: 4 | AL100: 4 | AM100: 4 | AN100: 4
C101: Активный темп продаж | D101: =IF(D$98<='Исходные данные'!$D$10,0,D100*'Исходные данные'!$D$73) -> 0 | E101: =IF(E$98<='Исходные данные'!$D$10,0,E100*'Исходные данные'!$D$73) -> 0 | F101: =IF(F$98<='Исходные данные'!$D$10,0,F100*'Исходные данные'!$D$73) -> 0 | G101: =IF(G$98<='Исходные данные'!$D$10,0,G100*'Исходные данные'!$D$73) -> 0 | H101: =IF(H$98<='Исходные данные'!$D$10,0,H100*'Исходные данные'!$D$73) -> 0 | I101: =IF(I$98<='Исходные данные'!$D$10,0,I100*'Исходные данные'!$D$73) -> 1 | J101: =IF(J$98<='Исходные данные'!$D$10,0,J100*'Исходные данные'!$D$73) -> 1 | K101: =IF(K$98<='Исходные данные'!$D$10,0,K100*'Исходные данные'!$D$73) -> 1 | ... AN101: =IF(AN$98<='Исходные данные'!$D$10,0,AN100*'Исходные данные'!$D$73) -> 4
C104: Число клиентов в прогнозе допускает дроби: это математическое ожидание воронки и оттока, а не список заключённых договоров. Рыночная стоимость труда рассчитана по средним зарплатным ориентирам DreamJob (Россия, 2026, на руки), пересчитанным в начисленную зарплату. Тарифы взносов 2026 года приняты постоянными плановыми параметрами для следующих лет.
C106: В модели нет кредита, процентов, дивидендов и терминальной стоимости. Возврат команде рассчитывается для общего пула, без распределения по участникам. Учебный труд основателей оценивается управленчески. Пул возврата включает оценку начисленной зарплаты и бюджет взносов. Это не разрешение отсрочить обязательные выплаты по трудовым договорам. НДС, налог с выручки и зарплатные взносы считаются отдельно.
C108: Доли маркетинга, оценки ставок оплаты ролей и разовые клиентские расходы также редактируются на расчётных листах; они отмечены синим.

Sheet Готовность к рынку
C2: Готовность к рынку
C4: Сценарий: | D4: ='Исходные данные'!$G$5 -> Базовый
C6: Критерий | D6: Оценка 0–1 | E6: Что подтверждено / не подтверждено
C7: Соответствие целевым задачам | D7: 0.7 | E7: Концепция и сценарии описаны, интервью покупателей не представлены
C8: Качество интерфейса | D8: 0.7 | E8: Есть демо в практике 3
C9: Работоспособность и стабильность | D9: 0.3 | E9: Нет результатов нагрузочных и приёмочных испытаний
C10: Документация | D10: 0.5 | E10: Есть учебные описания, нет полного эксплуатационного комплекта
C11: Безопасность | D11: 0.3 | E11: Роли и правила доступа запланированы, проверки не представлены
C12: Эффект у клиента | D12: 0.3 | E12: Сокращение времени на 30% — цель, не измеренный результат
C13: Известность бренда | D13: 0.1 | E13: Доказательства клиентской базы отсутствуют
C14: Сервис и сопровождение | D14: 0.3 | E14: Предложена модель поддержки
C15: Стоимость покупки и эксплуатации | D15: 0.4 | E15: Есть тарифная гипотеза, готовность платить не подтверждена
C17: Готовность к коммерциализации | D17: =IF(COUNT(D7:D15)=9,AVERAGE(D7:D15),NA()) -> 0.4
C18: Интерпретация | D18: =IF(D17<0.3,"Ранняя стадия",IF(D17<0.7,"Требует доработки","Готовность требует фактической проверки")) -> Требует доработки
C21: Оценки — предварительное суждение по представленным материалам, не опрос трёх экспертов и не результаты тестирования.
C23: Коэффициент нормирован как средняя оценка критериев. Это исправляет отсутствие нормирования по числу критериев в формуле пособия.

Sheet COCOMO и разработка
C2: COCOMO и разработка
C4: Сценарий: | D4: ='Исходные данные'!$G$5 -> Базовый
C6: Модель COCOMO II | D6: Значение | E6: Единица | F6: Обоснование
C7: A | D7: 2.94
C8: B | D8: 0.91
C9: SIZE | D9: ='Исходные данные'!$D$61 -> 1.5 | E9: KSLOC
C11: Фактор масштаба | D11: Значение | E11: Уровень | F11: Обоснование
C12: PREC | D12: 1.25 | E12: Средний | F12: Некоторый опыт продукта и платформы
C13: FLEX | D13: 4 | E13: Средний | F13: Согласованные границы MVP
C14: RESL | D14: 4.24 | E14: Средний | F14: Риски доступа к данным и качества моделей
C15: TEAM | D15: 3.29 | E15: Средний | F15: Учебная команда из четрыех участников
C16: PMAT | D16: 4.68 | E16: Средний | F16: Процессы требуют формализации
C18: Показатель степени E | D18: =D8+0.01*SUM(D12:D16) -> 1.0846
C20: Множитель трудоёмкости | D20: Значение | E20: Уровень | F20: Обоснование
C21: PERS | D21: 1 | E21: Нормальный | F21: Оценка квалификации
C22: PREX | D22: 1 | E22: Нормальный | F22: Оценка опыта
C23: RCPX | D23: 1.33 | E23: Высокий | F23: Анализ текстов и интеграции
C24: RUSE | D24: 1 | E24: Нормальный | F24: Повторно используемое ядро
C25: PDIF | D25: 1 | E25: Нормальный | F25: Типовая серверная платформа
C26: FCIL | D26: 0.87 | E26: Высокий | F26: Готовые инструменты разработки
C27: SCED | D27: 1 | E27: Нормальный | F27: Без принудительного сжатия сроков
C29: EAF | D29: =PRODUCT(D21:D27) -> 1.1571
C30: Трудоёмкость разработки | D30: =D7*D29*D9^D18 -> 5.2808861 | E30: чел.-мес.
C33: Роль / работа | D33: Доля от PM | E33: Чел.-мес. | F33: Начислено, ₽/мес. | G33: ФОТ, ₽ | H33: Средняя на руки, ₽/мес. | I33: Единые взносы, ₽ | J33: Травматизм, ₽ | K33: Полная стоимость, ₽ | L33: Источник зарплаты | M33: Число анкет | N33: Проверено
C34: Проектирование | D34: 0.35 | E34: =$D$30*D34 -> 1.8483101 | F34: =IF(H34*12<=2088000,H34/0.87,IF(H34*12<=4298000,(H34*12-48000)/0.85/12,IF(H34*12<=16598000,(H34*12-198000)/0.82/12,IF(H34*12<=40598000,(H34*12-598000)/0.8/12,(H34*12-1598000)/0.78/12)))) -> 195402.3 | G34: =E34*F34 -> 361164.05 | H34: 170000 | I34: =G34/$G$41*$I$69 -> 108349.22 | J34: =G34*'Исходные данные'!$D$30 -> 722.3281 | K34: =SUM(G34,I34:J34) -> 470235.6 | L34: https://dreamjob.ru/salary/sistemnyy-analitik | M34: 175 | N34: 46311
C35: Разработка | D35: 1 | E35: =$D$30*D35 -> 5.2808861 | F35: =IF(H35*12<=2088000,H35/0.87,IF(H35*12<=4298000,(H35*12-48000)/0.85/12,IF(H35*12<=16598000,(H35*12-198000)/0.82/12,IF(H35*12<=40598000,(H35*12-598000)/0.8/12,(H35*12-1598000)/0.78/12)))) -> 166666.67 | G35: =E35*F35 -> 880147.69 | H35: 145000 | I35: =G35/$G$41*$I$69 -> 264044.31 | J35: =G35*'Исходные данные'!$D$30 -> 1760.2954 | K35: =SUM(G35,I35:J35) -> 1145952.3 | L35: https://dreamjob.ru/salary/python-razrabotchik | M35: 38 | N35: 46311
C36: Тестирование | D36: 0.5 | E36: =$D$30*D36 -> 2.6404431 | F36: =IF(H36*12<=2088000,H36/0.87,IF(H36*12<=4298000,(H36*12-48000)/0.85/12,IF(H36*12<=16598000,(H36*12-198000)/0.82/12,IF(H36*12<=40598000,(H36*12-598000)/0.8/12,(H36*12-1598000)/0.78/12)))) -> 149425.29 | G36: =E36*F36 -> 394548.96 | H36: 130000 | I36: =G36/$G$41*$I$69 -> 118364.69 | J36: =G36*'Исходные данные'!$D$30 -> 789.09793 | K36: =SUM(G36,I36:J36) -> 513702.75 | L36: https://dreamjob.ru/salary/testirovschik | M36: 286 | N36: 46311
C37: Нагрузочное тестирование | D37: 0.05 | E37: =$D$30*D37 -> 0.26404431 | F37: =IF(H37*12<=2088000,H37/0.87,IF(H37*12<=4298000,(H37*12-48000)/0.85/12,IF(H37*12<=16598000,(H37*12-198000)/0.82/12,IF(H37*12<=40598000,(H37*12-598000)/0.8/12,(H37*12-1598000)/0.78/12)))) -> 126436.78 | G37: =E37*F37 -> 33384.912 | H37: 110000 | I37: =G37/$G$41*$I$69 -> 10015.474 | J37: =G37*'Исходные данные'!$D$30 -> 66.769825 | K37: =SUM(G37,I37:J37) -> 43467.156 | L37: https://dreamjob.ru/salary/inzhener-po-nagruzochnomu-testirovaniyu | M37: 4 | N37: 46311
C38: Первоначальное внедрение | D38: 0.05 | E38: =$D$30*D38 -> 0.26404431 | F38: =IF(H38*12<=2088000,H38/0.87,IF(H38*12<=4298000,(H38*12-48000)/0.85/12,IF(H38*12<=16598000,(H38*12-198000)/0.82/12,IF(H38*12<=40598000,(H38*12-598000)/0.8/12,(H38*12-1598000)/0.78/12)))) -> 222352.94 | G38: =E38*F38 -> 58711.028 | H38: 193000 | I38: =G38/$G$41*$I$69 -> 17613.308 | J38: =G38*'Исходные данные'!$D$30 -> 117.42206 | K38: =SUM(G38,I38:J38) -> 76441.759 | L38: https://dreamjob.ru/salary/devops-inzhener | M38: не указано | N38: 46311
C39: Документация | D39: 0.05 | E39: =$D$30*D39 -> 0.26404431 | F39: =IF(H39*12<=2088000,H39/0.87,IF(H39*12<=4298000,(H39*12-48000)/0.85/12,IF(H39*12<=16598000,(H39*12-198000)/0.82/12,IF(H39*12<=40598000,(H39*12-598000)/0.8/12,(H39*12-1598000)/0.78/12)))) -> 166666.67 | G39: =E39*F39 -> 44007.384 | H39: 145000 | I39: =G39/$G$41*$I$69 -> 13202.215 | J39: =G39*'Исходные данные'!$D$30 -> 88.014769 | K39: =SUM(G39,I39:J39) -> 57297.615 | L39: https://dreamjob.ru/salary/tehnicheskiy-pisatel | M39: 25 | N39: 46311
C41: Итого ФОТ / средняя ставка | E41: =SUM(E34:E39) -> 10.561772 | F41: =G41/E41 -> 167771.47 | G41: =SUM(G34:G39) -> 1771964 | I41: =SUM(I34:I39) -> 531589.21 | J41: =SUM(J34:J39) -> 3543.9281 | K41: =SUM(K34:K39) -> 2307097.2
C42: Обязательные взносы работодателя | G42: =SUM(I69:J69) -> 535133.14
C43: Труд и взносы / полная ставка | F43: =G43/E41 -> 218438.45 | G43: =SUM(G41:G42) -> 2307097.2
C45: Требуемая средняя занятость | D45: =E41/'Исходные данные'!$D$10 -> 2.6404431 | E45: FTE
C46: Доступная ёмкость команды | D46: ='Исходные данные'!$D$11*'Исходные данные'!$D$10 -> 16 | E46: чел.-мес.
C47: Отклонение от ёмкости | D47: =E41-D46 -> -5.4382277 | E47: чел.-мес.
C48: Согласованность срока | D48: =IF(D47>0,"Нужно сократить MVP / увеличить срок","Ёмкость достаточна") -> Ёмкость достаточна
C50: SIZE оценён по шести модулям MVP: коннекторы 0,30; очистка 0,15; анализ 0,35; события 0,20; интерфейс 0,35; доступ 0,15 KSLOC.
C52: ФОТ — рыночная оценка труда учебной команды, а не зарплата к выплате сейчас. Возврат 50% свободного потока моделируется отдельно. При найме работников сроки зарплаты и взносов определяются законодательством, а не наличием продаж.
C54: Доли ролей из пособия использованы как учебная калькуляция. COCOMO может учитывать часть сопутствующих работ; оценку необходимо сверить с фактическими часами.
C56: DreamJob: средние месячные зарплаты по самоотчётам по России, 2026, на руки. Это не официальная статистика всех работников. Малые выборки особенно ограничивают оценку нагрузочного тестирования (4 анкеты). Для внедрения выбран DevOps как функциональный аналог.
C58: Ставка F = эквивалент начисленной зарплаты по годовой прогрессивной шкале НДФЛ. НДФЛ уже входит в ФОТ и не добавляется сверху. Средняя ставка = общий ФОТ / общая трудоёмкость, не простое среднее шести ролей. https://www.nalog.gov.ru/rn48/promo/new2025/
C60: Взносы: 30% до годовой базы 2 979 000 ₽ на человека, 15,1% сверх неё; травматизм 0,2% — допущение I класса. Льготы ИТ не применены. https://www.nalog.gov.ru/rn77/news/activities_fts/16577139/ https://sfr.gov.ru/employers/insurance_premiums_tariffs~8297
C62: Шесть видов работ распределены между четырьмя участниками. Взносы рассчитаны помесячно по каждому участнику с обнулением базы в новом календарном году. Учитывается только оплата этого проекта. Тарифы 2026 сохранены для прогноза; внешние доходы участников неизвестны.
C64: Участник / совмещение | E64: Чел.-мес. | F64: Загрузка за срок | G64: ФОТ, ₽ | I64: Единые взносы, ₽ | J64: Травматизм, ₽ | K64: Полная стоимость, ₽
C65: 1: аналитика и документация | E65: =SUM(E34,E39) -> 2.1123545 | F65: =E65/'Исходные данные'!$D$10 -> 0.52808861 | G65: =SUM(G34,G39) -> 405171.44 | I65: =SUM(D84:AN84) -> 121551.43 | J65: =G65*'Исходные данные'!$D$30 -> 810.34287 | K65: =SUM(G65,I65:J65) -> 527533.21
C66: 2: разработка 50% | E66: =E35/2 -> 2.6404431 | F66: =E66/'Исходные данные'!$D$10 -> 0.66011077 | G66: =G35/2 -> 440073.84 | I66: =SUM(D85:AN85) -> 132022.15 | J66: =G66*'Исходные данные'!$D$30 -> 880.14769 | K66: =SUM(G66,I66:J66) -> 572976.15
C67: 3: разработка 50% и внедрение | E67: =E35/2+E38 -> 2.9044874 | F67: =E67/'Исходные данные'!$D$10 -> 0.72612184 | G67: =G35/2+G38 -> 498784.87 | I67: =SUM(D86:AN86) -> 149635.46 | J67: =G67*'Исходные данные'!$D$30 -> 997.56975 | K67: =SUM(G67,I67:J67) -> 649417.9
C68: 4: тестирование и нагрузка | E68: =SUM(E36:E37) -> 2.9044874 | F68: =E68/'Исходные данные'!$D$10 -> 0.72612184 | G68: =SUM(G36:G37) -> 427933.88 | I68: =SUM(D87:AN87) -> 128380.16 | J68: =G68*'Исходные данные'!$D$30 -> 855.86775 | K68: =SUM(G68,I68:J68) -> 557169.91
C69: Итого: 4 участника | E69: =SUM(E65:E68) -> 10.561772 | G69: =SUM(G65:G68) -> 1771964 | I69: =SUM(I65:I68) -> 531589.21 | J69: =SUM(J65:J68) -> 3543.9281 | K69: =SUM(K65:K68) -> 2307097.2
C71: Перегрузка участника, чел.-мес. | G71: =MAX(0,MAX(E65:E68)-'Исходные данные'!D10) -> 0
C73: Помесячная база и единые взносы по 4 участникам
C75: Месяц модели | D75: ='Продажи и потоки'!D6 -> 0 | E75: ='Продажи и потоки'!E6 -> 1 | F75: ='Продажи и потоки'!F6 -> 2 | G75: ='Продажи и потоки'!G6 -> 3 | H75: ='Продажи и потоки'!H6 -> 4 | I75: ='Продажи и потоки'!I6 -> 5 | J75: ='Продажи и потоки'!J6 -> 6 | K75: ='Продажи и потоки'!K6 -> 7 | ... AN75: ='Продажи и потоки'!AN6 -> 36
C76: Календарный год | D76: ='Продажи и потоки'!D8 -> 2026 | E76: ='Продажи и потоки'!E8 -> 2026 | F76: ='Продажи и потоки'!F8 -> 2026 | G76: ='Продажи и потоки'!G8 -> 2027 | H76: ='Продажи и потоки'!H8 -> 2027 | I76: ='Продажи и потоки'!I8 -> 2027 | J76: ='Продажи и потоки'!J8 -> 2027 | K76: ='Продажи и потоки'!K8 -> 2027 | ... AN76: ='Продажи и потоки'!AN8 -> 2029
C78: ФОТ участника 1 | D78: =IF(AND(D$75>0,D$75<='Исходные данные'!$D$10),$G65/'Исходные данные'!$D$10,0) -> 0 | E78: =IF(AND(E$75>0,E$75<='Исходные данные'!$D$10),$G65/'Исходные данные'!$D$10,0) -> 101292.86 | F78: =IF(AND(F$75>0,F$75<='Исходные данные'!$D$10),$G65/'Исходные данные'!$D$10,0) -> 101292.86 | G78: =IF(AND(G$75>0,G$75<='Исходные данные'!$D$10),$G65/'Исходные данные'!$D$10,0) -> 101292.86 | H78: =IF(AND(H$75>0,H$75<='Исходные данные'!$D$10),$G65/'Исходные данные'!$D$10,0) -> 101292.86 | I78: =IF(AND(I$75>0,I$75<='Исходные данные'!$D$10),$G65/'Исходные данные'!$D$10,0) -> 0 | J78: =IF(AND(J$75>0,J$75<='Исходные данные'!$D$10),$G65/'Исходные данные'!$D$10,0) -> 0 | K78: =IF(AND(K$75>0,K$75<='Исходные данные'!$D$10),$G65/'Исходные данные'!$D$10,0) -> 0 | ... AN78: =IF(AND(AN$75>0,AN$75<='Исходные данные'!$D$10),$G65/'Исходные данные'!$D$10,0) -> 0
C79: ФОТ участника 2 | D79: =IF(AND(D$75>0,D$75<='Исходные данные'!$D$10),$G66/'Исходные данные'!$D$10,0) -> 0 | E79: =IF(AND(E$75>0,E$75<='Исходные данные'!$D$10),$G66/'Исходные данные'!$D$10,0) -> 110018.46 | F79: =IF(AND(F$75>0,F$75<='Исходные данные'!$D$10),$G66/'Исходные данные'!$D$10,0) -> 110018.46 | G79: =IF(AND(G$75>0,G$75<='Исходные данные'!$D$10),$G66/'Исходные данные'!$D$10,0) -> 110018.46 | H79: =IF(AND(H$75>0,H$75<='Исходные данные'!$D$10),$G66/'Исходные данные'!$D$10,0) -> 110018.46 | I79: =IF(AND(I$75>0,I$75<='Исходные данные'!$D$10),$G66/'Исходные данные'!$D$10,0) -> 0 | J79: =IF(AND(J$75>0,J$75<='Исходные данные'!$D$10),$G66/'Исходные данные'!$D$10,0) -> 0 | K79: =IF(AND(K$75>0,K$75<='Исходные данные'!$D$10),$G66/'Исходные данные'!$D$10,0) -> 0 | ... AN79: =IF(AND(AN$75>0,AN$75<='Исходные данные'!$D$10),$G66/'Исходные данные'!$D$10,0) -> 0
C80: ФОТ участника 3 | D80: =IF(AND(D$75>0,D$75<='Исходные данные'!$D$10),$G67/'Исходные данные'!$D$10,0) -> 0 | E80: =IF(AND(E$75>0,E$75<='Исходные данные'!$D$10),$G67/'Исходные данные'!$D$10,0) -> 124696.22 | F80: =IF(AND(F$75>0,F$75<='Исходные данные'!$D$10),$G67/'Исходные данные'!$D$10,0) -> 124696.22 | G80: =IF(AND(G$75>0,G$75<='Исходные данные'!$D$10),$G67/'Исходные данные'!$D$10,0) -> 124696.22 | H80: =IF(AND(H$75>0,H$75<='Исходные данные'!$D$10),$G67/'Исходные данные'!$D$10,0) -> 124696.22 | I80: =IF(AND(I$75>0,I$75<='Исходные данные'!$D$10),$G67/'Исходные данные'!$D$10,0) -> 0 | J80: =IF(AND(J$75>0,J$75<='Исходные данные'!$D$10),$G67/'Исходные данные'!$D$10,0) -> 0 | K80: =IF(AND(K$75>0,K$75<='Исходные данные'!$D$10),$G67/'Исходные данные'!$D$10,0) -> 0 | ... AN80: =IF(AND(AN$75>0,AN$75<='Исходные данные'!$D$10),$G67/'Исходные данные'!$D$10,0) -> 0
C81: ФОТ участника 4 | D81: =IF(AND(D$75>0,D$75<='Исходные данные'!$D$10),$G68/'Исходные данные'!$D$10,0) -> 0 | E81: =IF(AND(E$75>0,E$75<='Исходные данные'!$D$10),$G68/'Исходные данные'!$D$10,0) -> 106983.47 | F81: =IF(AND(F$75>0,F$75<='Исходные данные'!$D$10),$G68/'Исходные данные'!$D$10,0) -> 106983.47 | G81: =IF(AND(G$75>0,G$75<='Исходные данные'!$D$10),$G68/'Исходные данные'!$D$10,0) -> 106983.47 | H81: =IF(AND(H$75>0,H$75<='Исходные данные'!$D$10),$G68/'Исходные данные'!$D$10,0) -> 106983.47 | I81: =IF(AND(I$75>0,I$75<='Исходные данные'!$D$10),$G68/'Исходные данные'!$D$10,0) -> 0 | J81: =IF(AND(J$75>0,J$75<='Исходные данные'!$D$10),$G68/'Исходные данные'!$D$10,0) -> 0 | K81: =IF(AND(K$75>0,K$75<='Исходные данные'!$D$10),$G68/'Исходные данные'!$D$10,0) -> 0 | ... AN81: =IF(AND(AN$75>0,AN$75<='Исходные данные'!$D$10),$G68/'Исходные данные'!$D$10,0) -> 0
C84: Взносы участника 1 | D84: =MIN(D78,MAX(0,'Исходные данные'!$D$29-(SUMIFS($D78:D78,$D$76:D$76,D$76)-D78)))*'Исходные данные'!$D$15+MAX(0,D78-MAX(0,'Исходные данные'!$D$29-(SUMIFS($D78:D78,$D$76:D$76,D$76)-D78)))*'Исходные данные'!$D$31 -> 0 | E84: =MIN(E78,MAX(0,'Исходные данные'!$D$29-(SUMIFS($D78:E78,$D$76:E$76,E$76)-E78)))*'Исходные данные'!$D$15+MAX(0,E78-MAX(0,'Исходные данные'!$D$29-(SUMIFS($D78:E78,$D$76:E$76,E$76)-E78)))*'Исходные данные'!$D$31 -> 30387.858 | F84: =MIN(F78,MAX(0,'Исходные данные'!$D$29-(SUMIFS($D78:F78,$D$76:F$76,F$76)-F78)))*'Исходные данные'!$D$15+MAX(0,F78-MAX(0,'Исходные данные'!$D$29-(SUMIFS($D78:F78,$D$76:F$76,F$76)-F78)))*'Исходные данные'!$D$31 -> 30387.858 | G84: =MIN(G78,MAX(0,'Исходные данные'!$D$29-(SUMIFS($D78:G78,$D$76:G$76,G$76)-G78)))*'Исходные данные'!$D$15+MAX(0,G78-MAX(0,'Исходные данные'!$D$29-(SUMIFS($D78:G78,$D$76:G$76,G$76)-G78)))*'Исходные данные'!$D$31 -> 30387.858 | H84: =MIN(H78,MAX(0,'Исходные данные'!$D$29-(SUMIFS($D78:H78,$D$76:H$76,H$76)-H78)))*'Исходные данные'!$D$15+MAX(0,H78-MAX(0,'Исходные данные'!$D$29-(SUMIFS($D78:H78,$D$76:H$76,H$76)-H78)))*'Исходные данные'!$D$31 -> 30387.858 | I84: =MIN(I78,MAX(0,'Исходные данные'!$D$29-(SUMIFS($D78:I78,$D$76:I$76,I$76)-I78)))*'Исходные данные'!$D$15+MAX(0,I78-MAX(0,'Исходные данные'!$D$29-(SUMIFS($D78:I78,$D$76:I$76,I$76)-I78)))*'Исходные данные'!$D$31 -> 0 | J84: =MIN(J78,MAX(0,'Исходные данные'!$D$29-(SUMIFS($D78:J78,$D$76:J$76,J$76)-J78)))*'Исходные данные'!$D$15+MAX(0,J78-MAX(0,'Исходные данные'!$D$29-(SUMIFS($D78:J78,$D$76:J$76,J$76)-J78)))*'Исходные данные'!$D$31 -> 0 | K84: =MIN(K78,MAX(0,'Исходные данные'!$D$29-(SUMIFS($D78:K78,$D$76:K$76,K$76)-K78)))*'Исходные данные'!$D$15+MAX(0,K78-MAX(0,'Исходные данные'!$D$29-(SUMIFS($D78:K78,$D$76:K$76,K$76)-K78)))*'Исходные данные'!$D$31 -> 0 | ... AN84: =MIN(AN78,MAX(0,'Исходные данные'!$D$29-(SUMIFS($D78:AN78,$D$76:AN$76,AN$76)-AN78)))*'Исходные данные'!$D$15+MAX(0,AN78-MAX(0,'Исходные данные'!$D$29-(SUMIFS($D78:AN78,$D$76:AN$76,AN$76)-AN78)))*'Исходные данные'!$D$31 -> 0
C85: Взносы участника 2 | D85: =MIN(D79,MAX(0,'Исходные данные'!$D$29-(SUMIFS($D79:D79,$D$76:D$76,D$76)-D79)))*'Исходные данные'!$D$15+MAX(0,D79-MAX(0,'Исходные данные'!$D$29-(SUMIFS($D79:D79,$D$76:D$76,D$76)-D79)))*'Исходные данные'!$D$31 -> 0 | E85: =MIN(E79,MAX(0,'Исходные данные'!$D$29-(SUMIFS($D79:E79,$D$76:E$76,E$76)-E79)))*'Исходные данные'!$D$15+MAX(0,E79-MAX(0,'Исходные данные'!$D$29-(SUMIFS($D79:E79,$D$76:E$76,E$76)-E79)))*'Исходные данные'!$D$31 -> 33005.538 | F85: =MIN(F79,MAX(0,'Исходные данные'!$D$29-(SUMIFS($D79:F79,$D$76:F$76,F$76)-F79)))*'Исходные данные'!$D$15+MAX(0,F79-MAX(0,'Исходные данные'!$D$29-(SUMIFS($D79:F79,$D$76:F$76,F$76)-F79)))*'Исходные данные'!$D$31 -> 33005.538 | G85: =MIN(G79,MAX(0,'Исходные данные'!$D$29-(SUMIFS($D79:G79,$D$76:G$76,G$76)-G79)))*'Исходные данные'!$D$15+MAX(0,G79-MAX(0,'Исходные данные'!$D$29-(SUMIFS($D79:G79,$D$76:G$76,G$76)-G79)))*'Исходные данные'!$D$31 -> 33005.538 | H85: =MIN(H79,MAX(0,'Исходные данные'!$D$29-(SUMIFS($D79:H79,$D$76:H$76,H$76)-H79)))*'Исходные данные'!$D$15+MAX(0,H79-MAX(0,'Исходные данные'!$D$29-(SUMIFS($D79:H79,$D$76:H$76,H$76)-H79)))*'Исходные данные'!$D$31 -> 33005.538 | I85: =MIN(I79,MAX(0,'Исходные данные'!$D$29-(SUMIFS($D79:I79,$D$76:I$76,I$76)-I79)))*'Исходные данные'!$D$15+MAX(0,I79-MAX(0,'Исходные данные'!$D$29-(SUMIFS($D79:I79,$D$76:I$76,I$76)-I79)))*'Исходные данные'!$D$31 -> 0 | J85: =MIN(J79,MAX(0,'Исходные данные'!$D$29-(SUMIFS($D79:J79,$D$76:J$76,J$76)-J79)))*'Исходные данные'!$D$15+MAX(0,J79-MAX(0,'Исходные данные'!$D$29-(SUMIFS($D79:J79,$D$76:J$76,J$76)-J79)))*'Исходные данные'!$D$31 -> 0 | K85: =MIN(K79,MAX(0,'Исходные данные'!$D$29-(SUMIFS($D79:K79,$D$76:K$76,K$76)-K79)))*'Исходные данные'!$D$15+MAX(0,K79-MAX(0,'Исходные данные'!$D$29-(SUMIFS($D79:K79,$D$76:K$76,K$76)-K79)))*'Исходные данные'!$D$31 -> 0 | ... AN85: =MIN(AN79,MAX(0,'Исходные данные'!$D$29-(SUMIFS($D79:AN79,$D$76:AN$76,AN$76)-AN79)))*'Исходные данные'!$D$15+MAX(0,AN79-MAX(0,'Исходные данные'!$D$29-(SUMIFS($D79:AN79,$D$76:AN$76,AN$76)-AN79)))*'Исходные данные'!$D$31 -> 0
C86: Взносы участника 3 | D86: =MIN(D80,MAX(0,'Исходные данные'!$D$29-(SUMIFS($D80:D80,$D$76:D$76,D$76)-D80)))*'Исходные данные'!$D$15+MAX(0,D80-MAX(0,'Исходные данные'!$D$29-(SUMIFS($D80:D80,$D$76:D$76,D$76)-D80)))*'Исходные данные'!$D$31 -> 0 | E86: =MIN(E80,MAX(0,'Исходные данные'!$D$29-(SUMIFS($D80:E80,$D$76:E$76,E$76)-E80)))*'Исходные данные'!$D$15+MAX(0,E80-MAX(0,'Исходные данные'!$D$29-(SUMIFS($D80:E80,$D$76:E$76,E$76)-E80)))*'Исходные данные'!$D$31 -> 37408.865 | F86: =MIN(F80,MAX(0,'Исходные данные'!$D$29-(SUMIFS($D80:F80,$D$76:F$76,F$76)-F80)))*'Исходные данные'!$D$15+MAX(0,F80-MAX(0,'Исходные данные'!$D$29-(SUMIFS($D80:F80,$D$76:F$76,F$76)-F80)))*'Исходные данные'!$D$31 -> 37408.865 | G86: =MIN(G80,MAX(0,'Исходные данные'!$D$29-(SUMIFS($D80:G80,$D$76:G$76,G$76)-G80)))*'Исходные данные'!$D$15+MAX(0,G80-MAX(0,'Исходные данные'!$D$29-(SUMIFS($D80:G80,$D$76:G$76,G$76)-G80)))*'Исходные данные'!$D$31 -> 37408.865 | H86: =MIN(H80,MAX(0,'Исходные данные'!$D$29-(SUMIFS($D80:H80,$D$76:H$76,H$76)-H80)))*'Исходные данные'!$D$15+MAX(0,H80-MAX(0,'Исходные данные'!$D$29-(SUMIFS($D80:H80,$D$76:H$76,H$76)-H80)))*'Исходные данные'!$D$31 -> 37408.865 | I86: =MIN(I80,MAX(0,'Исходные данные'!$D$29-(SUMIFS($D80:I80,$D$76:I$76,I$76)-I80)))*'Исходные данные'!$D$15+MAX(0,I80-MAX(0,'Исходные данные'!$D$29-(SUMIFS($D80:I80,$D$76:I$76,I$76)-I80)))*'Исходные данные'!$D$31 -> 0 | J86: =MIN(J80,MAX(0,'Исходные данные'!$D$29-(SUMIFS($D80:J80,$D$76:J$76,J$76)-J80)))*'Исходные данные'!$D$15+MAX(0,J80-MAX(0,'Исходные данные'!$D$29-(SUMIFS($D80:J80,$D$76:J$76,J$76)-J80)))*'Исходные данные'!$D$31 -> 0 | K86: =MIN(K80,MAX(0,'Исходные данные'!$D$29-(SUMIFS($D80:K80,$D$76:K$76,K$76)-K80)))*'Исходные данные'!$D$15+MAX(0,K80-MAX(0,'Исходные данные'!$D$29-(SUMIFS($D80:K80,$D$76:K$76,K$76)-K80)))*'Исходные данные'!$D$31 -> 0 | ... AN86: =MIN(AN80,MAX(0,'Исходные данные'!$D$29-(SUMIFS($D80:AN80,$D$76:AN$76,AN$76)-AN80)))*'Исходные данные'!$D$15+MAX(0,AN80-MAX(0,'Исходные данные'!$D$29-(SUMIFS($D80:AN80,$D$76:AN$76,AN$76)-AN80)))*'Исходные данные'!$D$31 -> 0
C87: Взносы участника 4 | D87: =MIN(D81,MAX(0,'Исходные данные'!$D$29-(SUMIFS($D81:D81,$D$76:D$76,D$76)-D81)))*'Исходные данные'!$D$15+MAX(0,D81-MAX(0,'Исходные данные'!$D$29-(SUMIFS($D81:D81,$D$76:D$76,D$76)-D81)))*'Исходные данные'!$D$31 -> 0 | E87: =MIN(E81,MAX(0,'Исходные данные'!$D$29-(SUMIFS($D81:E81,$D$76:E$76,E$76)-E81)))*'Исходные данные'!$D$15+MAX(0,E81-MAX(0,'Исходные данные'!$D$29-(SUMIFS($D81:E81,$D$76:E$76,E$76)-E81)))*'Исходные данные'!$D$31 -> 32095.041 | F87: =MIN(F81,MAX(0,'Исходные данные'!$D$29-(SUMIFS($D81:F81,$D$76:F$76,F$76)-F81)))*'Исходные данные'!$D$15+MAX(0,F81-MAX(0,'Исходные данные'!$D$29-(SUMIFS($D81:F81,$D$76:F$76,F$76)-F81)))*'Исходные данные'!$D$31 -> 32095.041 | G87: =MIN(G81,MAX(0,'Исходные данные'!$D$29-(SUMIFS($D81:G81,$D$76:G$76,G$76)-G81)))*'Исходные данные'!$D$15+MAX(0,G81-MAX(0,'Исходные данные'!$D$29-(SUMIFS($D81:G81,$D$76:G$76,G$76)-G81)))*'Исходные данные'!$D$31 -> 32095.041 | H87: =MIN(H81,MAX(0,'Исходные данные'!$D$29-(SUMIFS($D81:H81,$D$76:H$76,H$76)-H81)))*'Исходные данные'!$D$15+MAX(0,H81-MAX(0,'Исходные данные'!$D$29-(SUMIFS($D81:H81,$D$76:H$76,H$76)-H81)))*'Исходные данные'!$D$31 -> 32095.041 | I87: =MIN(I81,MAX(0,'Исходные данные'!$D$29-(SUMIFS($D81:I81,$D$76:I$76,I$76)-I81)))*'Исходные данные'!$D$15+MAX(0,I81-MAX(0,'Исходные данные'!$D$29-(SUMIFS($D81:I81,$D$76:I$76,I$76)-I81)))*'Исходные данные'!$D$31 -> 0 | J87: =MIN(J81,MAX(0,'Исходные данные'!$D$29-(SUMIFS($D81:J81,$D$76:J$76,J$76)-J81)))*'Исходные данные'!$D$15+MAX(0,J81-MAX(0,'Исходные данные'!$D$29-(SUMIFS($D81:J81,$D$76:J$76,J$76)-J81)))*'Исходные данные'!$D$31 -> 0 | K87: =MIN(K81,MAX(0,'Исходные данные'!$D$29-(SUMIFS($D81:K81,$D$76:K$76,K$76)-K81)))*'Исходные данные'!$D$15+MAX(0,K81-MAX(0,'Исходные данные'!$D$29-(SUMIFS($D81:K81,$D$76:K$76,K$76)-K81)))*'Исходные данные'!$D$31 -> 0 | ... AN87: =MIN(AN81,MAX(0,'Исходные данные'!$D$29-(SUMIFS($D81:AN81,$D$76:AN$76,AN$76)-AN81)))*'Исходные данные'!$D$15+MAX(0,AN81-MAX(0,'Исходные данные'!$D$29-(SUMIFS($D81:AN81,$D$76:AN$76,AN$76)-AN81)))*'Исходные данные'!$D$31 -> 0

Sheet CAPEX OPEX TCO
C2: CAPEX OPEX TCO
C4: Сценарий: | D4: ='Исходные данные'!$G$5 -> Базовый
C6: Начальные затраты разработчика | D6: Сумма, руб.
C7: Начальные денежные расходы | D7: ='Исходные данные'!$D$16 -> 30000
C8: Денежные расходы за разработку | D8: ='Исходные данные'!$D$17*'Исходные данные'!$D$10 -> 60000
C9: Оценка труда команды | D9: ='COCOMO и разработка'!G41 -> 1771964
C10: Обязательные страховые взносы | D10: ='COCOMO и разработка'!G42 -> 535133.14
C11: Полная стоимость создания MVP | D11: =SUM(D7:D10,D14:D15) -> 2424769.2
C12: Из неё деньги на старте | D12: =SUM(D7:D8,D15) -> 90000
C13: Управленческий пул труда и взносов | D13: =SUM(D9:D10) -> 2307097.2
C14: Износ оборудования за разработку | D14: ='Оборудование и амортизация'!F29 -> 27672
C15: Новая закупка оборудования | D15: ='Оборудование и амортизация'!F27 -> 0
C16: Расходы после запуска | D16: Активно, руб. | E16: Единица
C17: Постоянные расходы | D17: ='Исходные данные'!$D$65 -> 80000 | E17: руб./мес.
C18: Обслуживание клиента | D18: ='Исходные данные'!$D$45 -> 5000 | E18: руб./клиент/мес.
C19: Подключение нового клиента | D19: ='Исходные данные'!$D$49 -> 15000 | E19: руб./клиент
C20: Привлечение нового клиента | D20: ='Исходные данные'!$D$53 -> 15000 | E20: руб./клиент
C23: Затраты разработчика за 36 мес. | D23: Сумма, руб.
C24: Денежные расходы без компенсации | D24: =SUM('Продажи и потоки'!D31:AN31) -> 13485705
C25: Фактически выплаченная компенсация | D25: =SUM('Продажи и потоки'!D39:AN39) -> 2307097.2
C26: Все денежные выплаты | D26: =SUM(D24:D25) -> 15792802
C27: Ресурсная стоимость с износом | D27: =D24-D15+D13+'Оборудование и амортизация'!F30 -> 16041850
C28: Остаток пула компенсации | D28: ='Продажи и потоки'!AN40 -> 0
C31: TCO одного клиента | D31: Сумма, руб.
C32: Первоначальное внедрение (CAPEX*) | D32: ='Исходные данные'!$D$37 -> 50000
C33: Оборудование клиента | D33: 0
C34: Внутреннее обучение / настройка клиента | D34: 10000
C35: Подписка за период (OPEX) | D35: ='Исходные данные'!$D$33*'Исходные данные'!$D$21 -> 720000
C36: Внутреннее администрирование в месяц | D36: 2000
C37: Внутреннее администрирование за период | D37: =D36*'Исходные данные'!$D$21 -> 72000
C38: Совокупная стоимость владения | D38: =SUM(D32:D35)+D37 -> 852000
C41: В полной стоимости MVP отдельно учтён износ оборудования. В денежном бюджете — только новая закупка (сейчас 0 ₽). В ресурсной стоимости за 36 месяцев закупка заменена износом, чтобы не считать её дважды. Возврат труда не включает амортизацию.
C43: TCO клиента: цены с возможным НДС, без вычетов; обучение и внутреннее администрирование — учебные допущения, не поступления Cyberbara.
C45: Денежные выплаты и стоимость ресурсов различаются: начисленная оценка труда не списывается повторно вместе с компенсацией.

Sheet Тарифы и юнит-экономика
C2: Тарифы и юнит-экономика
C4: Сценарий: | D4: ='Исходные данные'!$G$5 -> Базовый
C6: Показатель | D6: Значение | E6: Единица
C7: Подписка | D7: ='Исходные данные'!$D$33 -> 20000 | E7: руб./мес.
C8: Внедрение | D8: ='Исходные данные'!$D$37 -> 50000 | E8: руб.
C9: Переменные затраты | D9: ='Исходные данные'!$D$45 -> 5000 | E9: руб./мес.
C10: Налоговый резерв с подписки | D10: =D7*'Исходные данные'!$D$13 -> 1200 | E10: руб./мес.
C11: Маржинальный доход до НДС | D11: =D7-SUM(D9:D10) -> 13800 | E11: руб./мес.
C12: Маржинальность | D12: =D11/D7 -> 0.69 | E12: доля
C13: Маркетинг и продажи за горизонт | D13: =SUM('Продажи и потоки'!D27:AN27)+SUM('Продажи и потоки'!D28:AN28)*10000/80000 -> 1853400 | E13: руб.
C14: Новые клиенты за горизонт | D14: =SUM('Продажи и потоки'!D14:AN14) -> 96 | E14: клиенты
C15: CAC с долей постоянного маркетинга | D15: =IF(D14=0,"n.a.",D13/D14) -> 19306.25 | E15: руб./клиент
C16: Ожидаемые оплаченные месяцы | D16: =IF('Исходные данные'!$D$41=0,'Исходные данные'!$D$20,(1-(1-'Исходные данные'!$D$41)^'Исходные данные'!$D$20)/'Исходные данные'!$D$41) -> 19.210983 | E16: месяцы
C17: LTV по выручке | D17: =D7*D16 -> 384219.66 | E17: руб.
C18: LTV по маржинальному доходу | D18: =D11*D16 -> 265111.57 | E18: руб.
C19: LTV маржа / CAC | D19: =IF(AND(ISNUMBER(D15),D15>0),D18/D15,"n.a.") -> 13.731904 | E19: раз
C20: Постоянные расходы и износ в месяц | D20: ='Исходные данные'!$D$65+'Оборудование и амортизация'!F31 -> 86918 | E20: руб./мес.
C21: Экономическая безубыточность, клиентов | D21: =IF(D11<=0,"n.a.",ROUNDUP(D20/D11,0)) -> 7 | E21: клиенты
C22: Маржа внедрения после налога и CAC | D22: =D8*(1-'Исходные данные'!$D$13)-'Исходные данные'!$D$49-'Исходные данные'!$D$53 -> 17000 | E22: руб./клиент
C23: LTV с маржой внедрения до CAC | D23: =D18+D8*(1-'Исходные данные'!$D$13)-'Исходные данные'!$D$49 -> 297111.57 | E23: руб.
C27: Цена с возвратом труда | D27: Значение | E27: Единица
C28: Распределение постоянных расходов | D28: =D20/'Исходные данные'!$D$18 -> 2897.2667 | E28: руб./клиент/мес.
C29: Возмещение CAC за срок жизни | D29: =IF(ISNUMBER(D15),D15/D16,"n.a.") -> 1004.959 | E29: руб./клиент/мес.
C30: Возврат труда, взносов и износа разработки | D30: =('COCOMO и разработка'!G43+'Оборудование и амортизация'!F29)/('Исходные данные'!$D$18*'Исходные данные'!$D$19) -> 3242.735 | E30: руб./клиент/мес.
C31: Полная расчётная нагрузка | D31: =SUM(D9,D28:D30) -> 12144.961 | E31: руб./клиент/мес.
C32: Минимальная цена до НДС | D32: =IF(ISNUMBER(D29),D31/(1-'Исходные данные'!$D$13),"n.a.") -> 12920.171 | E32: руб./мес.
C33: Минимальная цена с резервом НДС | D33: =IF(ISNUMBER(D32),D32*(1+'Исходные данные'!$D$14),"n.a.") -> 13566.179 | E33: руб./мес.
C34: Разница тарифа и ценового ориентира | D34: =IF(ISNUMBER(D33),D7-D33,"n.a.") -> 6433.8206 | E34: руб./мес.
C37: Цена включает возмещение труда через маржу подписки, а не отдельную повторную надбавку клиенту. Фактический возврат зависит от продаж и правила 50%.
C39: LTV и безубыточность — стартовые ориентиры до НДС и индексации расходов; детальная налоговая и кассовая динамика рассчитана на листе потоков.
C41: CAC включает переменный бюджет привлечения и 12,5% постоянных расходов (в базе 10 из 80 тыс. руб.); доля — допущение.
C43: Простой LTV не дисконтирован. Первоначальное внедрение не включено в основной LTV, его вклад показан отдельно.
C44: Минимальная цена учитывает ФОТ с обязательными взносами, износ ПК за разработку и последующий ежемесячный износ. Объём клиентов и срок возврата — учебные допущения. Амортизация не входит в кассовые расходы и не выплачивается участникам.
C45: Оплаченные месяцы для LTV = сумма вероятностей сохранения клиента за 24 месяца; учитывается месячный отток. Стоимость труда возвращается через маржу.

Sheet Оборудование и амортизация
C2: Оборудование: восстановительная стоимость и управленческая амортизация
C3: Четыре компьютера уже имеются. Спецификация ниже оценивает стоимость сопоставимого парка, а не подтверждает фактическую покупку.
C5: Требуется рабочих мест | F5: ='Исходные данные'!D11 -> 4
C6: Уже имеется рабочих мест | F6: 4
C7: Новых рабочих мест к покупке | F7: =MAX(0,F5-F6) -> 0
C8: Срок полезного использования, мес. | F8: 36
C9: Доля использования в проекте | F9: 1
C10: Остаточная доля стоимости | F10: 0
C12: Компонент | D12: Модель / артикул | E12: Кол-во на 1 место | F12: Цена за единицу, ₽ | G12: На 1 место, ₽ | H12: Весь парк, ₽ | I12: Новая закупка, ₽ | J12: Ссылка на товар в магазине | K12: Проверено
C13: Процессор с графикой | D13: AMD Ryzen 5 5600GT OEM | E13: 1 | F13: 13472 | G13: =E13*F13 -> 13472 | H13: =G13*$F$5 -> 53888 | I13: =G13*$F$7 -> 0 | J13: https://www.kns.ru/product/processor-amd-ryzen-5-5600gt-oem/ | K13: 46311
C14: Материнская плата | D14: MSI A520M-A PRO, AM4 | E14: 1 | F14: 4210 | G14: =E14*F14 -> 4210 | H14: =G14*$F$5 -> 16840 | I14: =G14*$F$7 -> 0 | J14: https://www.kns.ru/product/materinskaya-plata-msi-a520m-a-pro/ | K14: 46311
C15: Оперативная память | D15: Patriot PVS416G320C6K, 2×8 ГБ DDR4 | E15: 1 | F15: 15409 | G15: =E15*F15 -> 15409 | H15: =G15*$F$5 -> 61636 | I15: =G15*$F$7 -> 0 | J15: https://www.kns.ru/product/operativnaya-pamyat-patriot-pvs416g320c6k/ | K15: 46311
C16: SSD | D16: Kingston NV3 500 ГБ SNV3S/500G | E16: 1 | F16: 11241 | G16: =E16*F16 -> 11241 | H16: =G16*$F$5 -> 44964 | I16: =G16*$F$7 -> 0 | J16: https://www.kns.ru/product/ssd-disk-kingston-nv3-500gb-snv3s-500g/ | K16: 46311
C17: Блок питания | D17: Deepcool PF450, 450 Вт | E17: 1 | F17: 3246 | G17: =E17*F17 -> 3246 | H17: =G17*$F$5 -> 12984 | I17: =G17*$F$7 -> 0 | J17: https://www.kns.ru/product/blok-pitaniya-deepcool-450w-pf450/ | K17: 46311
C18: Корпус | D18: Zalman T6 Black, без БП | E18: 1 | F18: 3961 | G18: =E18*F18 -> 3961 | H18: =G18*$F$5 -> 15844 | I18: =G18*$F$7 -> 0 | J18: https://www.kns.ru/product/korpus-zalman-t6-black/ | K18: 46311
C19: Охлаждение CPU | D19: ID-Cooling SE-903-XT V2 ARGB | E19: 1 | F19: 1156 | G19: =E19*F19 -> 1156 | H19: =G19*$F$5 -> 4624 | I19: =G19*$F$7 -> 0 | J19: https://www.kns.ru/product/kuler-id-cooling-se-903-xt-v2-argb/ | K19: 46311
C20: Монитор | D20: Lime T238A, 23,8″ IPS Full HD | E20: 1 | F20: 7293 | G20: =E20*F20 -> 7293 | H20: =G20*$F$5 -> 29172 | I20: =G20*$F$7 -> 0 | J20: https://www.kns.ru/product/monitor-lime-t238a/ | K20: 46311
C21: Клавиатура и мышь | D21: Logitech MK120, 920-002561, USB | E21: 1 | F21: 2189 | G21: =E21*F21 -> 2189 | H21: =G21*$F$5 -> 8756 | I21: =G21*$F$7 -> 0 | J21: https://www.kns.ru/product/klaviatura-logitech-920-002561/ | K21: 46311
C22: Термопаста | D22: ID-Cooling Frost X05, тюбик 5 г | E22: 0.25 | F22: 340 | G22: =E22*F22 -> 85 | H22: =G22*$F$5 -> 340 | I22: =G22*$F$7 -> 0 | J22: https://www.kns.ru/product/termopasta-id-cooling-frost-x05-5gr/ | K22: 46311
C25: Стоимость одного рабочего места | F25: =SUM(G13:G22) -> 62262
C26: Стоимость требуемого парка | F26: =SUM(H13:H22) -> 249048
C27: Денежная закупка новых мест | F27: =SUM(I13:I22) -> 0
C28: Амортизация всего парка, ₽/мес. | F28: =F26*(1-F10)/F8*F9 -> 6918
C29: Амортизация за разработку | F29: =F28*MIN('Исходные данные'!D10,F8) -> 27672
C30: Амортизация за горизонт модели | F30: =F28*MIN(MAX('Продажи и потоки'!D6:AN6),F8) -> 249048
C31: Амортизация первого месяца эксплуатации | F31: =IF('Исходные данные'!D10<F8,F28,0) -> 6918
C34: Цены KNS, розничный снимок на 16.10.2026, с НДС поставщика, без вычета входного НДС. Автоматического обновления цен из интернета нет. Перед закупкой цены и наличие необходимо уточнить.
C36: 36 месяцев, нулевая остаточная стоимость и 100% использования — изменяемые учебные допущения. Для имеющихся ПК это управленческая оценка износа по восстановительной стоимости, не бухгалтерская или налоговая амортизация.
C38: Минимальная конфигурация для веб-разработки и прототипа NLP: 6 ядер, 16 ГБ ОЗУ, SSD 500 ГБ, встроенная графика. Тяжёлые вычисления вынесены на сервер из OPEX. Сеть, кабели и действующие лицензии предполагаются имеющимися; новой оплаты нет.
C40: Один тюбик термопасты распределён на четыре места. Перед реальным заказом проверить поддержку CPU версией BIOS, габариты охлаждения и комплект кабелей. Это ценовой ориентир, а не готовая заявка поставщику.

Sheet Продажи и потоки
C2: Продажи и потоки
C4: Сценарий: | D4: ='Исходные данные'!$G$5 -> Базовый
C6: Период, месяц | D6: 0 | E6: 1 | F6: 2 | G6: 3 | H6: 4 | I6: 5 | J6: 6 | K6: 7 | L6: 8 | M6: 9 | N6: 10 | O6: 11 | P6: 12 | Q6: 13 | R6: 14 | S6: 15 | T6: 16 | U6: 17 | V6: 18 | W6: 19 | X6: 20 | Y6: 21 | Z6: 22 | AA6: 23 | AB6: 24 | AC6: 25 | AD6: 26 | AE6: 27 | AF6: 28 | AG6: 29 | AH6: 30 | AI6: 31 | AJ6: 32 | AK6: 33 | AL6: 34 | AM6: 35 | AN6: 36
C7: Дата | D7: =EDATE('Исходные данные'!$D$9,D6-1) -> 46296 | E7: =EDATE('Исходные данные'!$D$9,E6-1) -> 46327 | F7: =EDATE('Исходные данные'!$D$9,F6-1) -> 46357 | G7: =EDATE('Исходные данные'!$D$9,G6-1) -> 46388 | H7: =EDATE('Исходные данные'!$D$9,H6-1) -> 46419 | I7: =EDATE('Исходные данные'!$D$9,I6-1) -> 46447 | J7: =EDATE('Исходные данные'!$D$9,J6-1) -> 46478 | K7: =EDATE('Исходные данные'!$D$9,K6-1) -> 46508 | ... AN7: =EDATE('Исходные данные'!$D$9,AN6-1) -> 47392
C8: Календарный год | D8: =YEAR(D7) -> 2026 | E8: =YEAR(E7) -> 2026 | F8: =YEAR(F7) -> 2026 | G8: =YEAR(G7) -> 2027 | H8: =YEAR(H7) -> 2027 | I8: =YEAR(I7) -> 2027 | J8: =YEAR(J7) -> 2027 | K8: =YEAR(K7) -> 2027 | ... AN8: =YEAR(AN7) -> 2029
C9: Порог НДС за год, руб. | D9: =IF(D8<=2026,'Исходные данные'!$D$26,IF(D8=2027,'Исходные данные'!$D$27,'Исходные данные'!$D$28)) -> 20000000 | E9: =IF(E8<=2026,'Исходные данные'!$D$26,IF(E8=2027,'Исходные данные'!$D$27,'Исходные данные'!$D$28)) -> 20000000 | F9: =IF(F8<=2026,'Исходные данные'!$D$26,IF(F8=2027,'Исходные данные'!$D$27,'Исходные данные'!$D$28)) -> 20000000 | G9: =IF(G8<=2026,'Исходные данные'!$D$26,IF(G8=2027,'Исходные данные'!$D$27,'Исходные данные'!$D$28)) -> 15000000 | H9: =IF(H8<=2026,'Исходные данные'!$D$26,IF(H8=2027,'Исходные данные'!$D$27,'Исходные данные'!$D$28)) -> 15000000 | I9: =IF(I8<=2026,'Исходные данные'!$D$26,IF(I8=2027,'Исходные данные'!$D$27,'Исходные данные'!$D$28)) -> 15000000 | J9: =IF(J8<=2026,'Исходные данные'!$D$26,IF(J8=2027,'Исходные данные'!$D$27,'Исходные данные'!$D$28)) -> 15000000 | K9: =IF(K8<=2026,'Исходные данные'!$D$26,IF(K8=2027,'Исходные данные'!$D$27,'Исходные данные'!$D$28)) -> 15000000 | ... AN9: =IF(AN8<=2026,'Исходные данные'!$D$26,IF(AN8=2027,'Исходные данные'!$D$27,'Исходные данные'!$D$28)) -> 10000000
C10: Поступления с начала года | D10: =SUMIFS($D$22:D$22,$D$8:D$8,D8) -> 0 | E10: =SUMIFS($D$22:E$22,$D$8:E$8,E8) -> 0 | F10: =SUMIFS($D$22:F$22,$D$8:F$8,F8) -> 0 | G10: =SUMIFS($D$22:G$22,$D$8:G$8,G8) -> 0 | H10: =SUMIFS($D$22:H$22,$D$8:H$8,H8) -> 0 | I10: =SUMIFS($D$22:I$22,$D$8:I$8,I8) -> 70000 | J10: =SUMIFS($D$22:J$22,$D$8:J$8,J8) -> 159600 | K10: =SUMIFS($D$22:K$22,$D$8:K$8,K8) -> 268408 | ... AN10: =SUMIFS($D$22:AN$22,$D$8:AN$8,AN8) -> 14658412
C11: Поступления за предыдущий год | D11: =SUMIFS($D$22:$AN$22,$D$8:$AN$8,D8-1) -> 0 | E11: =SUMIFS($D$22:$AN$22,$D$8:$AN$8,E8-1) -> 0 | F11: =SUMIFS($D$22:$AN$22,$D$8:$AN$8,F8-1) -> 0 | G11: =SUMIFS($D$22:$AN$22,$D$8:$AN$8,G8-1) -> 0 | H11: =SUMIFS($D$22:$AN$22,$D$8:$AN$8,H8-1) -> 0 | I11: =SUMIFS($D$22:$AN$22,$D$8:$AN$8,I8-1) -> 0 | J11: =SUMIFS($D$22:$AN$22,$D$8:$AN$8,J8-1) -> 0 | K11: =SUMIFS($D$22:$AN$22,$D$8:$AN$8,K8-1) -> 0 | ... AN11: =SUMIFS($D$22:$AN$22,$D$8:$AN$8,AN8-1) -> 9864606.3
C12: Применение НДС: 1 / 0 | D12: =0 -> 0 | E12: =IF(OR(E11>E9,IF(D8=E8,D10,0)>E9),1,0) -> 0 | F12: =IF(OR(F11>F9,IF(E8=F8,E10,0)>F9),1,0) -> 0 | G12: =IF(OR(G11>G9,IF(F8=G8,F10,0)>G9),1,0) -> 0 | H12: =IF(OR(H11>H9,IF(G8=H8,G10,0)>H9),1,0) -> 0 | I12: =IF(OR(I11>I9,IF(H8=I8,H10,0)>I9),1,0) -> 0 | J12: =IF(OR(J11>J9,IF(I8=J8,I10,0)>J9),1,0) -> 0 | K12: =IF(OR(K11>K9,IF(J8=K8,J10,0)>K9),1,0) -> 0 | L12: =IF(OR(L11>L9,IF(K8=L8,K10,0)>L9),1,0) -> 0 | ... AN12: =IF(OR(AN11>AN9,IF(AM8=AN8,AM10,0)>AN9),1,0) -> 1
C13: Клиенты на начало месяца | D13: =0 -> 0 | E13: =D16 -> 0 | F13: =E16 -> 0 | G13: =F16 -> 0 | H13: =G16 -> 0 | I13: =H16 -> 0 | J13: =I16 -> 1 | K13: =J16 -> 1.98 | L13: =K16 -> 2.9404 | ... AN13: =AM16 -> 72.83896
C14: Новые клиенты | D14: ='Исходные данные'!D101 -> 0 | E14: ='Исходные данные'!E101 -> 0 | F14: ='Исходные данные'!F101 -> 0 | G14: ='Исходные данные'!G101 -> 0 | H14: ='Исходные данные'!H101 -> 0 | I14: ='Исходные данные'!I101 -> 1 | J14: ='Исходные данные'!J101 -> 1 | K14: ='Исходные данные'!K101 -> 1 | ... AN14: ='Исходные данные'!AN101 -> 4
C15: Ушедшие клиенты | D15: =D13*'Исходные данные'!$D$41 -> 0 | E15: =E13*'Исходные данные'!$D$41 -> 0 | F15: =F13*'Исходные данные'!$D$41 -> 0 | G15: =G13*'Исходные данные'!$D$41 -> 0 | H15: =H13*'Исходные данные'!$D$41 -> 0 | I15: =I13*'Исходные данные'!$D$41 -> 0 | J15: =J13*'Исходные данные'!$D$41 -> 0.02 | K15: =K13*'Исходные данные'!$D$41 -> 0.0396 | ... AN15: =AN13*'Исходные данные'!$D$41 -> 1.4567792
C16: Клиенты на конец месяца | D16: =SUM(D13:D14)-D15 -> 0 | E16: =SUM(E13:E14)-E15 -> 0 | F16: =SUM(F13:F14)-F15 -> 0 | G16: =SUM(G13:G14)-G15 -> 0 | H16: =SUM(H13:H14)-H15 -> 0 | I16: =SUM(I13:I14)-I15 -> 1 | J16: =SUM(J13:J14)-J15 -> 1.98 | K16: =SUM(K13:K14)-K15 -> 2.9404 | ... AN16: =SUM(AN13:AN14)-AN15 -> 75.382181
C17: Оплачиваемые клиенты за месяц | D17: =D16 -> 0 | E17: =E16 -> 0 | F17: =F16 -> 0 | G17: =G16 -> 0 | H17: =H16 -> 0 | I17: =I16 -> 1 | J17: =J16 -> 1.98 | K17: =K16 -> 2.9404 | ... AN17: =AN16 -> 75.382181
C18: Подписка на клиента | D18: ='Исходные данные'!$D$33 -> 20000 | E18: ='Исходные данные'!$D$33 -> 20000 | F18: ='Исходные данные'!$D$33 -> 20000 | G18: ='Исходные данные'!$D$33 -> 20000 | H18: ='Исходные данные'!$D$33 -> 20000 | I18: ='Исходные данные'!$D$33 -> 20000 | J18: ='Исходные данные'!$D$33 -> 20000 | K18: ='Исходные данные'!$D$33 -> 20000 | ... AN18: ='Исходные данные'!$D$33 -> 20000
C19: Внедрение на клиента | D19: ='Исходные данные'!$D$37 -> 50000 | E19: ='Исходные данные'!$D$37 -> 50000 | F19: ='Исходные данные'!$D$37 -> 50000 | G19: ='Исходные данные'!$D$37 -> 50000 | H19: ='Исходные данные'!$D$37 -> 50000 | I19: ='Исходные данные'!$D$37 -> 50000 | J19: ='Исходные данные'!$D$37 -> 50000 | K19: ='Исходные данные'!$D$37 -> 50000 | ... AN19: ='Исходные данные'!$D$37 -> 50000
C20: Поступления подписки | D20: =D17*D18 -> 0 | E20: =E17*E18 -> 0 | F20: =F17*F18 -> 0 | G20: =G17*G18 -> 0 | H20: =H17*H18 -> 0 | I20: =I17*I18 -> 20000 | J20: =J17*J18 -> 39600 | K20: =K17*K18 -> 58808 | ... AN20: =AN17*AN18 -> 1507643.6
C21: Поступления внедрения | D21: =D14*D19 -> 0 | E21: =E14*E19 -> 0 | F21: =F14*F19 -> 0 | G21: =G14*G19 -> 0 | H21: =H14*H19 -> 0 | I21: =I14*I19 -> 50000 | J21: =J14*J19 -> 50000 | K21: =K14*K19 -> 50000 | ... AN21: =AN14*AN19 -> 200000
C22: Всего поступления, включая НДС | D22: =SUM(D20:D21) -> 0 | E22: =SUM(E20:E21) -> 0 | F22: =SUM(F20:F21) -> 0 | G22: =SUM(G20:G21) -> 0 | H22: =SUM(H20:H21) -> 0 | I22: =SUM(I20:I21) -> 70000 | J22: =SUM(J20:J21) -> 89600 | K22: =SUM(K20:K21) -> 108808 | ... AN22: =SUM(AN20:AN21) -> 1707643.6
C23: НДС к перечислению | D23: =D22*D12*'Исходные данные'!$D$14/(1+'Исходные данные'!$D$14) -> 0 | E23: =E22*E12*'Исходные данные'!$D$14/(1+'Исходные данные'!$D$14) -> 0 | F23: =F22*F12*'Исходные данные'!$D$14/(1+'Исходные данные'!$D$14) -> 0 | G23: =G22*G12*'Исходные данные'!$D$14/(1+'Исходные данные'!$D$14) -> 0 | H23: =H22*H12*'Исходные данные'!$D$14/(1+'Исходные данные'!$D$14) -> 0 | I23: =I22*I12*'Исходные данные'!$D$14/(1+'Исходные данные'!$D$14) -> 0 | J23: =J22*J12*'Исходные данные'!$D$14/(1+'Исходные данные'!$D$14) -> 0 | K23: =K22*K12*'Исходные данные'!$D$14/(1+'Исходные данные'!$D$14) -> 0 | ... AN23: =AN22*AN12*'Исходные данные'!$D$14/(1+'Исходные данные'!$D$14) -> 81316.363
C24: Выручка без НДС | D24: =D22-D23 -> 0 | E24: =E22-E23 -> 0 | F24: =F22-F23 -> 0 | G24: =G22-G23 -> 0 | H24: =H22-H23 -> 0 | I24: =I22-I23 -> 70000 | J24: =J22-J23 -> 89600 | K24: =K22-K23 -> 108808 | ... AN24: =AN22-AN23 -> 1626327.3
C25: Переменные расходы обслуживания | D25: =D17*'Исходные данные'!$D$45*(1+'Исходные данные'!$D$69)^INT(MAX(0,D6-'Исходные данные'!$D$10-1)/12) -> 0 | E25: =E17*'Исходные данные'!$D$45*(1+'Исходные данные'!$D$69)^INT(MAX(0,E6-'Исходные данные'!$D$10-1)/12) -> 0 | F25: =F17*'Исходные данные'!$D$45*(1+'Исходные данные'!$D$69)^INT(MAX(0,F6-'Исходные данные'!$D$10-1)/12) -> 0 | G25: =G17*'Исходные данные'!$D$45*(1+'Исходные данные'!$D$69)^INT(MAX(0,G6-'Исходные данные'!$D$10-1)/12) -> 0 | H25: =H17*'Исходные данные'!$D$45*(1+'Исходные данные'!$D$69)^INT(MAX(0,H6-'Исходные данные'!$D$10-1)/12) -> 0 | I25: =I17*'Исходные данные'!$D$45*(1+'Исходные данные'!$D$69)^INT(MAX(0,I6-'Исходные данные'!$D$10-1)/12) -> 5000 | J25: =J17*'Исходные данные'!$D$45*(1+'Исходные данные'!$D$69)^INT(MAX(0,J6-'Исходные данные'!$D$10-1)/12) -> 9900 | K25: =K17*'Исходные данные'!$D$45*(1+'Исходные данные'!$D$69)^INT(MAX(0,K6-'Исходные данные'!$D$10-1)/12) -> 14702 | ... AN25: =AN17*'Исходные данные'!$D$45*(1+'Исходные данные'!$D$69)^INT(MAX(0,AN6-'Исходные данные'!$D$10-1)/12) -> 415544.27
C26: Внедрение новых клиентов | D26: =D14*'Исходные данные'!$D$49*(1+'Исходные данные'!$D$69)^INT(MAX(0,D6-'Исходные данные'!$D$10-1)/12) -> 0 | E26: =E14*'Исходные данные'!$D$49*(1+'Исходные данные'!$D$69)^INT(MAX(0,E6-'Исходные данные'!$D$10-1)/12) -> 0 | F26: =F14*'Исходные данные'!$D$49*(1+'Исходные данные'!$D$69)^INT(MAX(0,F6-'Исходные данные'!$D$10-1)/12) -> 0 | G26: =G14*'Исходные данные'!$D$49*(1+'Исходные данные'!$D$69)^INT(MAX(0,G6-'Исходные данные'!$D$10-1)/12) -> 0 | H26: =H14*'Исходные данные'!$D$49*(1+'Исходные данные'!$D$69)^INT(MAX(0,H6-'Исходные данные'!$D$10-1)/12) -> 0 | I26: =I14*'Исходные данные'!$D$49*(1+'Исходные данные'!$D$69)^INT(MAX(0,I6-'Исходные данные'!$D$10-1)/12) -> 15000 | J26: =J14*'Исходные данные'!$D$49*(1+'Исходные данные'!$D$69)^INT(MAX(0,J6-'Исходные данные'!$D$10-1)/12) -> 15000 | K26: =K14*'Исходные данные'!$D$49*(1+'Исходные данные'!$D$69)^INT(MAX(0,K6-'Исходные данные'!$D$10-1)/12) -> 15000 | ... AN26: =AN14*'Исходные данные'!$D$49*(1+'Исходные данные'!$D$69)^INT(MAX(0,AN6-'Исходные данные'!$D$10-1)/12) -> 66150
C27: Привлечение новых клиентов | D27: =D14*'Исходные данные'!$D$53*(1+'Исходные данные'!$D$69)^INT(MAX(0,D6-'Исходные данные'!$D$10-1)/12) -> 0 | E27: =E14*'Исходные данные'!$D$53*(1+'Исходные данные'!$D$69)^INT(MAX(0,E6-'Исходные данные'!$D$10-1)/12) -> 0 | F27: =F14*'Исходные данные'!$D$53*(1+'Исходные данные'!$D$69)^INT(MAX(0,F6-'Исходные данные'!$D$10-1)/12) -> 0 | G27: =G14*'Исходные данные'!$D$53*(1+'Исходные данные'!$D$69)^INT(MAX(0,G6-'Исходные данные'!$D$10-1)/12) -> 0 | H27: =H14*'Исходные данные'!$D$53*(1+'Исходные данные'!$D$69)^INT(MAX(0,H6-'Исходные данные'!$D$10-1)/12) -> 0 | I27: =I14*'Исходные данные'!$D$53*(1+'Исходные данные'!$D$69)^INT(MAX(0,I6-'Исходные данные'!$D$10-1)/12) -> 15000 | J27: =J14*'Исходные данные'!$D$53*(1+'Исходные данные'!$D$69)^INT(MAX(0,J6-'Исходные данные'!$D$10-1)/12) -> 15000 | K27: =K14*'Исходные данные'!$D$53*(1+'Исходные данные'!$D$69)^INT(MAX(0,K6-'Исходные данные'!$D$10-1)/12) -> 15000 | ... AN27: =AN14*'Исходные данные'!$D$53*(1+'Исходные данные'!$D$69)^INT(MAX(0,AN6-'Исходные данные'!$D$10-1)/12) -> 66150
C28: Постоянные расходы | D28: =IF(D6>'Исходные данные'!$D$10,'Исходные данные'!$D$65*(1+'Исходные данные'!$D$69)^INT(MAX(0,D6-'Исходные данные'!$D$10-1)/12),0) -> 0 | E28: =IF(E6>'Исходные данные'!$D$10,'Исходные данные'!$D$65*(1+'Исходные данные'!$D$69)^INT(MAX(0,E6-'Исходные данные'!$D$10-1)/12),0) -> 0 | F28: =IF(F6>'Исходные данные'!$D$10,'Исходные данные'!$D$65*(1+'Исходные данные'!$D$69)^INT(MAX(0,F6-'Исходные данные'!$D$10-1)/12),0) -> 0 | G28: =IF(G6>'Исходные данные'!$D$10,'Исходные данные'!$D$65*(1+'Исходные данные'!$D$69)^INT(MAX(0,G6-'Исходные данные'!$D$10-1)/12),0) -> 0 | H28: =IF(H6>'Исходные данные'!$D$10,'Исходные данные'!$D$65*(1+'Исходные данные'!$D$69)^INT(MAX(0,H6-'Исходные данные'!$D$10-1)/12),0) -> 0 | I28: =IF(I6>'Исходные данные'!$D$10,'Исходные данные'!$D$65*(1+'Исходные данные'!$D$69)^INT(MAX(0,I6-'Исходные данные'!$D$10-1)/12),0) -> 80000 | J28: =IF(J6>'Исходные данные'!$D$10,'Исходные данные'!$D$65*(1+'Исходные данные'!$D$69)^INT(MAX(0,J6-'Исходные данные'!$D$10-1)/12),0) -> 80000 | K28: =IF(K6>'Исходные данные'!$D$10,'Исходные данные'!$D$65*(1+'Исходные данные'!$D$69)^INT(MAX(0,K6-'Исходные данные'!$D$10-1)/12),0) -> 80000 | ... AN28: =IF(AN6>'Исходные данные'!$D$10,'Исходные данные'!$D$65*(1+'Исходные данные'!$D$69)^INT(MAX(0,AN6-'Исходные данные'!$D$10-1)/12),0) -> 88200
C29: Денежные расходы разработки | D29: =IF(AND(D6>0,D6<='Исходные данные'!$D$10),'Исходные данные'!$D$17,0) -> 0 | E29: =IF(AND(E6>0,E6<='Исходные данные'!$D$10),'Исходные данные'!$D$17,0) -> 15000 | F29: =IF(AND(F6>0,F6<='Исходные данные'!$D$10),'Исходные данные'!$D$17,0) -> 15000 | G29: =IF(AND(G6>0,G6<='Исходные данные'!$D$10),'Исходные данные'!$D$17,0) -> 15000 | H29: =IF(AND(H6>0,H6<='Исходные данные'!$D$10),'Исходные данные'!$D$17,0) -> 15000 | I29: =IF(AND(I6>0,I6<='Исходные данные'!$D$10),'Исходные данные'!$D$17,0) -> 0 | J29: =IF(AND(J6>0,J6<='Исходные данные'!$D$10),'Исходные данные'!$D$17,0) -> 0 | K29: =IF(AND(K6>0,K6<='Исходные данные'!$D$10),'Исходные данные'!$D$17,0) -> 0 | ... AN29: =IF(AND(AN6>0,AN6<='Исходные данные'!$D$10),'Исходные данные'!$D$17,0) -> 0
C30: Первоначальные денежные расходы | D30: ='Исходные данные'!$D$16+'Оборудование и амортизация'!$F$27 -> 30000 | E30: =0 -> 0 | F30: =0 -> 0 | G30: =0 -> 0 | H30: =0 -> 0 | I30: =0 -> 0 | J30: =0 -> 0 | K30: =0 -> 0 | L30: =0 -> 0 | ... AN30: =0 -> 0
C31: Все выплаты без компенсации | D31: =SUM(D25:D30)+D23+D32 -> 30000 | E31: =SUM(E25:E30)+E23+E32 -> 15000 | F31: =SUM(F25:F30)+F23+F32 -> 15000 | G31: =SUM(G25:G30)+G23+G32 -> 15000 | H31: =SUM(H25:H30)+H23+H32 -> 15000 | I31: =SUM(I25:I30)+I23+I32 -> 119200 | J31: =SUM(J25:J30)+J23+J32 -> 125276 | K31: =SUM(K25:K30)+K23+K32 -> 131230.48 | ... AN31: =SUM(AN25:AN30)+AN23+AN32 -> 814940.27
C32: Резерв налога с выручки | D32: =D24*'Исходные данные'!$D$13 -> 0 | E32: =E24*'Исходные данные'!$D$13 -> 0 | F32: =F24*'Исходные данные'!$D$13 -> 0 | G32: =G24*'Исходные данные'!$D$13 -> 0 | H32: =H24*'Исходные данные'!$D$13 -> 0 | I32: =I24*'Исходные данные'!$D$13 -> 4200 | J32: =J24*'Исходные данные'!$D$13 -> 5376 | K32: =K24*'Исходные данные'!$D$13 -> 6528.48 | ... AN32: =AN24*'Исходные данные'!$D$13 -> 97579.636
C33: CF до компенсации команде | D33: =D22-D31 -> -30000 | E33: =E22-E31 -> -15000 | F33: =F22-F31 -> -15000 | G33: =G22-G31 -> -15000 | H33: =H22-H31 -> -15000 | I33: =I22-I31 -> -49200 | J33: =J22-J31 -> -35676 | K33: =K22-K31 -> -22422.48 | ... AN33: =AN22-AN31 -> 892703.35
C34: Начисление оценки труда с резервом | D34: =IF(AND(D6>0,D6<='Исходные данные'!$D$10),'COCOMO и разработка'!$G$43/'Исходные данные'!$D$10,0) -> 0 | E34: =IF(AND(E6>0,E6<='Исходные данные'!$D$10),'COCOMO и разработка'!$G$43/'Исходные данные'!$D$10,0) -> 576774.29 | F34: =IF(AND(F6>0,F6<='Исходные данные'!$D$10),'COCOMO и разработка'!$G$43/'Исходные данные'!$D$10,0) -> 576774.29 | G34: =IF(AND(G6>0,G6<='Исходные данные'!$D$10),'COCOMO и разработка'!$G$43/'Исходные данные'!$D$10,0) -> 576774.29 | H34: =IF(AND(H6>0,H6<='Исходные данные'!$D$10),'COCOMO и разработка'!$G$43/'Исходные данные'!$D$10,0) -> 576774.29 | I34: =IF(AND(I6>0,I6<='Исходные данные'!$D$10),'COCOMO и разработка'!$G$43/'Исходные данные'!$D$10,0) -> 0 | J34: =IF(AND(J6>0,J6<='Исходные данные'!$D$10),'COCOMO и разработка'!$G$43/'Исходные данные'!$D$10,0) -> 0 | K34: =IF(AND(K6>0,K6<='Исходные данные'!$D$10),'COCOMO и разработка'!$G$43/'Исходные данные'!$D$10,0) -> 0 | ... AN34: =IF(AND(AN6>0,AN6<='Исходные данные'!$D$10),'COCOMO и разработка'!$G$43/'Исходные данные'!$D$10,0) -> 0
C35: Пул компенсации на начало | D35: =0 -> 0 | E35: =D40 -> 0 | F35: =E40 -> 576774.29 | G35: =F40 -> 1153548.6 | H35: =G40 -> 1730322.9 | I35: =H40 -> 2307097.2 | J35: =I40 -> 2307097.2 | K35: =J40 -> 2307097.2 | L35: =K40 -> 2307097.2 | ... AN35: =AM40 -> 0
C36: Кассовый итог на начало | D36: =0 -> 0 | E36: =D42 -> -30000 | F36: =E42 -> -45000 | G36: =F42 -> -60000 | H36: =G42 -> -75000 | I36: =H42 -> -90000 | J36: =I42 -> -139200 | K36: =J42 -> -174876 | L36: =K42 -> -197298.48 | ... AN36: =AM42 -> 10239957
C37: Положительный поток после дефицита | D37: =MAX(0,D33+MIN(0,D36)) -> 0 | E37: =MAX(0,E33+MIN(0,E36)) -> 0 | F37: =MAX(0,F33+MIN(0,F36)) -> 0 | G37: =MAX(0,G33+MIN(0,G36)) -> 0 | H37: =MAX(0,H33+MIN(0,H36)) -> 0 | I37: =MAX(0,I33+MIN(0,I36)) -> 0 | J37: =MAX(0,J33+MIN(0,J36)) -> 0 | K37: =MAX(0,K33+MIN(0,K36)) -> 0 | ... AN37: =MAX(0,AN33+MIN(0,AN36)) -> 892703.35
C38: Предельная доля на компенсацию | D38: =D37*'Исходные данные'!$D$12 -> 0 | E38: =E37*'Исходные данные'!$D$12 -> 0 | F38: =F37*'Исходные данные'!$D$12 -> 0 | G38: =G37*'Исходные данные'!$D$12 -> 0 | H38: =H37*'Исходные данные'!$D$12 -> 0 | I38: =I37*'Исходные данные'!$D$12 -> 0 | J38: =J37*'Исходные данные'!$D$12 -> 0 | K38: =K37*'Исходные данные'!$D$12 -> 0 | ... AN38: =AN37*'Исходные данные'!$D$12 -> 446351.68
C39: Выплата компенсации | D39: =MIN(SUM(D35,D34),D38) -> 0 | E39: =MIN(SUM(E35,E34),E38) -> 0 | F39: =MIN(SUM(F35,F34),F38) -> 0 | G39: =MIN(SUM(G35,G34),G38) -> 0 | H39: =MIN(SUM(H35,H34),H38) -> 0 | I39: =MIN(SUM(I35,I34),I38) -> 0 | J39: =MIN(SUM(J35,J34),J38) -> 0 | K39: =MIN(SUM(K35,K34),K38) -> 0 | ... AN39: =MIN(SUM(AN35,AN34),AN38) -> 0
C40: Пул компенсации на конец | D40: =SUM(D35,D34)-D39 -> 0 | E40: =SUM(E35,E34)-E39 -> 576774.29 | F40: =SUM(F35,F34)-F39 -> 1153548.6 | G40: =SUM(G35,G34)-G39 -> 1730322.9 | H40: =SUM(H35,H34)-H39 -> 2307097.2 | I40: =SUM(I35,I34)-I39 -> 2307097.2 | J40: =SUM(J35,J34)-J39 -> 2307097.2 | K40: =SUM(K35,K34)-K39 -> 2307097.2 | ... AN40: =SUM(AN35,AN34)-AN39 -> 0
C41: CF после компенсации | D41: =D33-D39 -> -30000 | E41: =E33-E39 -> -15000 | F41: =F33-F39 -> -15000 | G41: =G33-G39 -> -15000 | H41: =H33-H39 -> -15000 | I41: =I33-I39 -> -49200 | J41: =J33-J39 -> -35676 | K41: =K33-K39 -> -22422.48 | ... AN41: =AN33-AN39 -> 892703.35
C42: Кассовый итог на конец | D42: =D36+D41 -> -30000 | E42: =E36+E41 -> -45000 | F42: =F36+F41 -> -60000 | G42: =G36+G41 -> -75000 | H42: =H36+H41 -> -90000 | I42: =I36+I41 -> -139200 | J42: =J36+J41 -> -174876 | K42: =K36+K41 -> -197298.48 | ... AN42: =AN36+AN41 -> 11132660
C43: Экономический CF с оплатой труда | D43: =D33-D34 -> -30000 | E43: =E33-E34 -> -591774.29 | F43: =F33-F34 -> -591774.29 | G43: =G33-G34 -> -591774.29 | H43: =H33-H34 -> -591774.29 | I43: =I33-I34 -> -49200 | J43: =J33-J34 -> -35676 | K43: =K33-K34 -> -22422.48 | ... AN43: =AN33-AN34 -> 892703.35
C44: Накопленный экономический CF | D44: =D43 -> -30000 | E44: =D44+E43 -> -621774.29 | F44: =E44+F43 -> -1213548.6 | G44: =F44+G43 -> -1805322.9 | H44: =G44+H43 -> -2397097.2 | I44: =H44+I43 -> -2446297.2 | J44: =I44+J43 -> -2481973.2 | K44: =J44+K43 -> -2504395.6 | L44: =K44+L43 -> -2513829.7 | ... AN44: =AM44+AN43 -> 11132660
C45: Общий отток денег после компенсации | D45: =SUM(D31,D39) -> 30000 | E45: =SUM(E31,E39) -> 15000 | F45: =SUM(F31,F39) -> 15000 | G45: =SUM(G31,G39) -> 15000 | H45: =SUM(H31,H39) -> 15000 | I45: =SUM(I31,I39) -> 119200 | J45: =SUM(J31,J39) -> 125276 | K45: =SUM(K31,K39) -> 131230.48 | ... AN45: =SUM(AN31,AN39) -> 814940.27
C46: Ноль для графика | D46: =0 -> 0 | E46: =0 -> 0 | F46: =0 -> 0 | G46: =0 -> 0 | H46: =0 -> 0 | I46: =0 -> 0 | J46: =0 -> 0 | K46: =0 -> 0 | ... AN46: =0 -> 0
C49: Подписка оплачивается за весь месяц подключения; отток — в начале месяца. После запуска сопровождение и внедрение оплачиваются, даже если первоначальный труд отложен.
C51: Отрицательный кассовый итог показывает потребность во внешнем финансировании. Компенсация не выплачивается до покрытия накопленного дефицита.
C53: Экономический CF учитывает труд в месяцы разработки и не вычитает его повторно при компенсации. Кассовый CF учитывает только фактические выплаты.
C56: Амортизация отражает износ имеющихся компьютеров и входит в ресурсную себестоимость (строки 60–61). Это не платёж, поэтому денежный поток, касса и NPV не уменьшаются на неё повторно.
C60: Управленческая амортизация, не деньги | D60: =IF(AND(D$6>0,D$6<='Оборудование и амортизация'!$F$8),'Оборудование и амортизация'!$F$28,0) -> 0 | E60: =IF(AND(E$6>0,E$6<='Оборудование и амортизация'!$F$8),'Оборудование и амортизация'!$F$28,0) -> 6918 | F60: =IF(AND(F$6>0,F$6<='Оборудование и амортизация'!$F$8),'Оборудование и амортизация'!$F$28,0) -> 6918 | G60: =IF(AND(G$6>0,G$6<='Оборудование и амортизация'!$F$8),'Оборудование и амортизация'!$F$28,0) -> 6918 | H60: =IF(AND(H$6>0,H$6<='Оборудование и амортизация'!$F$8),'Оборудование и амортизация'!$F$28,0) -> 6918 | I60: =IF(AND(I$6>0,I$6<='Оборудование и амортизация'!$F$8),'Оборудование и амортизация'!$F$28,0) -> 6918 | J60: =IF(AND(J$6>0,J$6<='Оборудование и амортизация'!$F$8),'Оборудование и амортизация'!$F$28,0) -> 6918 | K60: =IF(AND(K$6>0,K$6<='Оборудование и амортизация'!$F$8),'Оборудование и амортизация'!$F$28,0) -> 6918 | ... AN60: =IF(AND(AN$6>0,AN$6<='Оборудование и амортизация'!$F$8),'Оборудование и амортизация'!$F$28,0) -> 6918
C61: Ресурсные затраты с износом | D61: =D31+D34+D60-IF(D$6=0,'Оборудование и амортизация'!$F$27,0) -> 30000 | E61: =E31+E34+E60-IF(E$6=0,'Оборудование и амортизация'!$F$27,0) -> 598692.29 | F61: =F31+F34+F60-IF(F$6=0,'Оборудование и амортизация'!$F$27,0) -> 598692.29 | G61: =G31+G34+G60-IF(G$6=0,'Оборудование и амортизация'!$F$27,0) -> 598692.29 | H61: =H31+H34+H60-IF(H$6=0,'Оборудование и амортизация'!$F$27,0) -> 598692.29 | I61: =I31+I34+I60-IF(I$6=0,'Оборудование и амортизация'!$F$27,0) -> 126118 | J61: =J31+J34+J60-IF(J$6=0,'Оборудование и амортизация'!$F$27,0) -> 132194 | K61: =K31+K34+K60-IF(K$6=0,'Оборудование и амортизация'!$F$27,0) -> 138148.48 | ... AN61: =AN31+AN34+AN60-IF(AN$6=0,'Оборудование и амортизация'!$F$27,0) -> 821858.27

Sheet NPV IRR окупаемость
C2: NPV IRR окупаемость
C4: Сценарий: | D4: ='Исходные данные'!$G$5 -> Базовый
C6: Показатель | D6: Экономический расчёт | E6: Кассовый после компенсации
C7: Годовая ставка | D7: ='Исходные данные'!$D$57 -> 0.25
C8: Месячная ставка | D8: =(1+D7)^(1/12)-1 -> 0.018769265
C10: NPV за 36 месяцев | D10: =SUM(D27:AN27) -> 5920462.3 | E10: =SUM(D31:AN31) -> 6525385.9
C11: IRR месячная | D11: =IF(AND(MIN('Продажи и потоки'!D43:AN43)<0,MAX('Продажи и потоки'!D43:AN43)>0),IFERROR(IRR('Продажи и потоки'!D43:AN43),"нет решения"),"нет смены знака") -> 0.077241366 | E11: =IF(AND(MIN('Продажи и потоки'!D41:AN41)<0,MAX('Продажи и потоки'!D41:AN41)>0),IFERROR(IRR('Продажи и потоки'!D41:AN41),"нет решения"),"нет смены знака") -> 0.22143838
C12: IRR годовая, эффективная | D12: =IF(ISNUMBER(D11),(1+D11)^12-1,"n.a.") -> 1.4420596 | E12: =IF(ISNUMBER(E11),(1+E11)^12-1,"n.a.") -> 10.027035
C13: DPP, месяцы от периода 0 | D13: =IF(MIN(D29:AN29)=999,"не достигнут",MIN(D29:AN29)) -> 21.694465 | E13: =IF(MIN(D33:AN33)=999,"не достигнут",MIN(D33:AN33)) -> 11.788397
C14: Пиковая потребность в деньгах | E14: =MAX(0,-MIN('Продажи и потоки'!D42:AN42)) -> 206732.51
C15: Компенсация команды: месяц погашения | E15: =IF(MIN(D34:AN34)=999,"не погашена",MIN(D34:AN34)) -> 25
C16: Остаток компенсации на конец | E16: ='Продажи и потоки'!AN40 -> 0
C17: NPV: решение по стоимости ресурсов | D17: =IF(D10>0,"Положительный NPV","Неположительный NPV") -> Положительный NPV
C23: Период, месяц | D23: ='Продажи и потоки'!D6 -> 0 | E23: ='Продажи и потоки'!E6 -> 1 | F23: ='Продажи и потоки'!F6 -> 2 | G23: ='Продажи и потоки'!G6 -> 3 | H23: ='Продажи и потоки'!H6 -> 4 | I23: ='Продажи и потоки'!I6 -> 5 | J23: ='Продажи и потоки'!J6 -> 6 | K23: ='Продажи и потоки'!K6 -> 7 | ... AN23: ='Продажи и потоки'!AN6 -> 36
C24: Дата | D24: ='Продажи и потоки'!D7 -> 46296 | E24: ='Продажи и потоки'!E7 -> 46327 | F24: ='Продажи и потоки'!F7 -> 46357 | G24: ='Продажи и потоки'!G7 -> 46388 | H24: ='Продажи и потоки'!H7 -> 46419 | I24: ='Продажи и потоки'!I7 -> 46447 | J24: ='Продажи и потоки'!J7 -> 46478 | K24: ='Продажи и потоки'!K7 -> 46508 | ... AN24: ='Продажи и потоки'!AN7 -> 47392
C25: Коэффициент дисконтирования | D25: =1/(1+$D$8)^D23 -> 1 | E25: =1/(1+$D$8)^E23 -> 0.98157653 | F25: =1/(1+$D$8)^F23 -> 0.96349248 | G25: =1/(1+$D$8)^G23 -> 0.94574161 | H25: =1/(1+$D$8)^H23 -> 0.92831777 | I25: =1/(1+$D$8)^I23 -> 0.91121493 | J25: =1/(1+$D$8)^J23 -> 0.89442719 | K25: =1/(1+$D$8)^K23 -> 0.87794874 | ... AN25: =1/(1+$D$8)^AN23 -> 0.512
C26: Экономический CF | D26: ='Продажи и потоки'!D43 -> -30000 | E26: ='Продажи и потоки'!E43 -> -591774.29 | F26: ='Продажи и потоки'!F43 -> -591774.29 | G26: ='Продажи и потоки'!G43 -> -591774.29 | H26: ='Продажи и потоки'!H43 -> -591774.29 | I26: ='Продажи и потоки'!I43 -> -49200 | J26: ='Продажи и потоки'!J43 -> -35676 | K26: ='Продажи и потоки'!K43 -> -22422.48 | ... AN26: ='Продажи и потоки'!AN43 -> 892703.35
C27: Дисконтированный экономический CF | D27: =D26*D25 -> -30000 | E27: =E26*E25 -> -580871.76 | F27: =F26*F25 -> -570170.08 | G27: =G26*G25 -> -559665.57 | H27: =H26*H25 -> -549354.59 | I27: =I26*I25 -> -44831.775 | J27: =J26*J25 -> -31909.584 | K27: =K26*K25 -> -19685.788 | ... AN27: =AN26*AN25 -> 457064.12
C28: Накопленный дисконтированный CF | D28: =D27 -> -30000 | E28: =D28+E27 -> -610871.76 | F28: =E28+F27 -> -1181041.8 | G28: =F28+G27 -> -1740707.4 | H28: =G28+H27 -> -2290062 | I28: =H28+I27 -> -2334893.8 | J28: =I28+J27 -> -2366803.4 | K28: =J28+K27 -> -2386489.1 | L28: =K28+L27 -> -2394619.1 | ... AN28: =AM28+AN27 -> 5920462.3
C29: Пересечение нуля: DPP экономический | D29: =999 -> 999 | E29: =IF(AND(D28<0,E28>=0),D23+ABS(D28)/E27,999) -> 999 | F29: =IF(AND(E28<0,F28>=0),E23+ABS(E28)/F27,999) -> 999 | G29: =IF(AND(F28<0,G28>=0),F23+ABS(F28)/G27,999) -> 999 | H29: =IF(AND(G28<0,H28>=0),G23+ABS(G28)/H27,999) -> 999 | I29: =IF(AND(H28<0,I28>=0),H23+ABS(H28)/I27,999) -> 999 | J29: =IF(AND(I28<0,J28>=0),I23+ABS(I28)/J27,999) -> 999 | K29: =IF(AND(J28<0,K28>=0),J23+ABS(J28)/K27,999) -> 999 | L29: =IF(AND(K28<0,L28>=0),K23+ABS(K28)/L27,999) -> 999 | ... AN29: =IF(AND(AM28<0,AN28>=0),AM23+ABS(AM28)/AN27,999) -> 999
C30: Кассовый CF после компенсации | D30: ='Продажи и потоки'!D41 -> -30000 | E30: ='Продажи и потоки'!E41 -> -15000 | F30: ='Продажи и потоки'!F41 -> -15000 | G30: ='Продажи и потоки'!G41 -> -15000 | H30: ='Продажи и потоки'!H41 -> -15000 | I30: ='Продажи и потоки'!I41 -> -49200 | J30: ='Продажи и потоки'!J41 -> -35676 | K30: ='Продажи и потоки'!K41 -> -22422.48 | ... AN30: ='Продажи и потоки'!AN41 -> 892703.35
C31: Дисконтированный кассовый CF | D31: =D30*D25 -> -30000 | E31: =E30*E25 -> -14723.648 | F31: =F30*F25 -> -14452.387 | G31: =G30*G25 -> -14186.124 | H31: =H30*H25 -> -13924.767 | I31: =I30*I25 -> -44831.775 | J31: =J30*J25 -> -31909.584 | K31: =K30*K25 -> -19685.788 | ... AN31: =AN30*AN25 -> 457064.12
C32: Накопленный дисконтированный CF кассы | D32: =D31 -> -30000 | E32: =D32+E31 -> -44723.648 | F32: =E32+F31 -> -59176.035 | G32: =F32+G31 -> -73362.159 | H32: =G32+H31 -> -87286.926 | I32: =H32+I31 -> -132118.7 | J32: =I32+J31 -> -164028.28 | K32: =J32+K31 -> -183714.07 | L32: =K32+L31 -> -191844.07 | ... AN32: =AM32+AN31 -> 6525385.9
C33: Пересечение нуля: DPP кассы | D33: =999 -> 999 | E33: =IF(AND(D32<0,E32>=0),D23+ABS(D32)/E31,999) -> 999 | F33: =IF(AND(E32<0,F32>=0),E23+ABS(E32)/F31,999) -> 999 | G33: =IF(AND(F32<0,G32>=0),F23+ABS(F32)/G31,999) -> 999 | H33: =IF(AND(G32<0,H32>=0),G23+ABS(G32)/H31,999) -> 999 | I33: =IF(AND(H32<0,I32>=0),H23+ABS(H32)/I31,999) -> 999 | J33: =IF(AND(I32<0,J32>=0),I23+ABS(I32)/J31,999) -> 999 | K33: =IF(AND(J32<0,K32>=0),J23+ABS(J32)/K31,999) -> 999 | L33: =IF(AND(K32<0,L32>=0),K23+ABS(K32)/L31,999) -> 999 | ... AN33: =IF(AND(AM32<0,AN32>=0),AM23+ABS(AM32)/AN31,999) -> 999
C34: Месяц погашения компенсации | D34: =IF(AND(D23>='Исходные данные'!$D$10,'Продажи и потоки'!D40<=0.01),D23,999) -> 999 | E34: =IF(AND(E23>='Исходные данные'!$D$10,'Продажи и потоки'!E40<=0.01),E23,999) -> 999 | F34: =IF(AND(F23>='Исходные данные'!$D$10,'Продажи и потоки'!F40<=0.01),F23,999) -> 999 | G34: =IF(AND(G23>='Исходные данные'!$D$10,'Продажи и потоки'!G40<=0.01),G23,999) -> 999 | H34: =IF(AND(H23>='Исходные данные'!$D$10,'Продажи и потоки'!H40<=0.01),H23,999) -> 999 | I34: =IF(AND(I23>='Исходные данные'!$D$10,'Продажи и потоки'!I40<=0.01),I23,999) -> 999 | J34: =IF(AND(J23>='Исходные данные'!$D$10,'Продажи и потоки'!J40<=0.01),J23,999) -> 999 | K34: =IF(AND(K23>='Исходные данные'!$D$10,'Продажи и потоки'!K40<=0.01),K23,999) -> 999 | ... AN34: =IF(AND(AN23>='Исходные данные'!$D$10,'Продажи и потоки'!AN40<=0.01),AN23,999) -> 36
C35: Ноль | D35: =0 -> 0 | E35: =0 -> 0 | F35: =0 -> 0 | G35: =0 -> 0 | H35: =0 -> 0 | I35: =0 -> 0 | J35: =0 -> 0 | K35: =0 -> 0 | ... AN35: =0 -> 0
C39: Месяц | D39: Экономический накопленный DCF | E39: Кассовый накопленный DCF | F39: Нулевая линия
C40: =D23 -> 0 | D40: =D28 -> -30000 | E40: =D32 -> -30000 | F40: =D35 -> 0
C41: =E23 -> 1 | D41: =E28 -> -610871.76 | E41: =E32 -> -44723.648 | F41: =E35 -> 0
C42: =F23 -> 2 | D42: =F28 -> -1181041.8 | E42: =F32 -> -59176.035 | F42: =F35 -> 0
C43: =G23 -> 3 | D43: =G28 -> -1740707.4 | E43: =G32 -> -73362.159 | F43: =G35 -> 0
C44: =H23 -> 4 | D44: =H28 -> -2290062 | E44: =H32 -> -87286.926 | F44: =H35 -> 0
C45: =I23 -> 5 | D45: =I28 -> -2334893.8 | E45: =I32 -> -132118.7 | F45: =I35 -> 0
C46: =J23 -> 6 | D46: =J28 -> -2366803.4 | E46: =J32 -> -164028.28 | F46: =J35 -> 0
C47: =K23 -> 7 | D47: =K28 -> -2386489.1 | E47: =K32 -> -183714.07 | F47: =K35 -> 0
C48: =L23 -> 8 | D48: =L28 -> -2394619.1 | E48: =L32 -> -191844.07 | F48: =L35 -> 0
C49: =M23 -> 9 | D49: =M28 -> -2365778.6 | E49: =M32 -> -163003.51 | F49: =M35 -> 0
C50: =N23 -> 10 | D50: =N28 -> -2315882.8 | E50: =N32 -> -113107.73 | F50: =N35 -> 0
C51: =O23 -> 11 | D51: =O28 -> -2246141.2 | E51: =O32 -> -43366.131 | F51: =O35 -> 0
C52: =P23 -> 12 | D52: =P28 -> -2157709.6 | E52: =P32 -> 11639.343 | F52: =P35 -> 0
C53: =Q23 -> 13 | D53: =Q28 -> -2027506.5 | E53: =Q32 -> 76740.912 | F53: =Q35 -> 0
C54: =R23 -> 14 | D54: =R28 -> -1870794.4 | E54: =R32 -> 155096.95 | F54: =R35 -> 0
C55: =S23 -> 15 | D55: =S28 -> -1689161.9 | E55: =S32 -> 245913.21 | F55: =S35 -> 0
C56: =T23 -> 16 | D56: =T28 -> -1484126.2 | E56: =T32 -> 348431.03 | F56: =T35 -> 0
C57: =U23 -> 17 | D57: =U28 -> -1267828 | E57: =U32 -> 456580.18 | F57: =U35 -> 0
C58: =V23 -> 18 | D58: =V28 -> -1031210.8 | E58: =V32 -> 574888.76 | F58: =V35 -> 0
C59: =W23 -> 19 | D59: =W28 -> -775573.96 | E59: =W32 -> 702707.17 | F59: =W35 -> 0
C60: =X23 -> 20 | D60: =X28 -> -502157.57 | E60: =X32 -> 839415.37 | F60: =X35 -> 0
C61: =Y23 -> 21 | D61: =Y28 -> -212145.01 | E61: =Y32 -> 984421.65 | F61: =Y35 -> 0
C62: =Z23 -> 22 | D62: =Z28 -> 93334.7 | E62: =Z32 -> 1137161.5 | F62: =Z35 -> 0
C63: =AA23 -> 23 | D63: =AA28 -> 413204.67 | E63: =AA32 -> 1297096.5 | F63: =AA35 -> 0
C64: =AB23 -> 24 | D64: =AB28 -> 746437.99 | E64: =AB32 -> 1463713.1 | F64: =AB35 -> 0
C65: =AC23 -> 25 | D65: =AC28 -> 1110305.1 | E65: =AC32 -> 1715228.7 | F65: =AC35 -> 0
C66: =AD23 -> 26 | D66: =AD28 -> 1493475.6 | E66: =AD32 -> 2098399.2 | F66: =AD35 -> 0
C67: =AE23 -> 27 | D67: =AE28 -> 1894604.1 | E67: =AE32 -> 2499527.7 | F67: =AE35 -> 0
C68: =AF23 -> 28 | D68: =AF28 -> 2312407.7 | E68: =AF32 -> 2917331.3 | F68: =AF35 -> 0
C69: =AG23 -> 29 | D69: =AG28 -> 2730898.2 | E69: =AG32 -> 3335821.8 | F69: =AG35 -> 0
C70: =AH23 -> 30 | D70: =AH28 -> 3163515.8 | E70: =AH32 -> 3768439.3 | F70: =AH35 -> 0
C71: =AI23 -> 31 | D71: =AI28 -> 3609169.2 | E71: =AI32 -> 4214092.7 | F71: =AI35 -> 0
C72: =AJ23 -> 32 | D72: =AJ28 -> 4066818.8 | E72: =AJ32 -> 4671742.4 | F72: =AJ35 -> 0
C73: =AK23 -> 33 | D73: =AK28 -> 4535474.8 | E73: =AK32 -> 5140398.3 | F73: =AK35 -> 0
C74: =AL23 -> 34 | D74: =AL28 -> 5014194.5 | E74: =AL32 -> 5619118.1 | F74: =AL35 -> 0
C75: =AM23 -> 35 | D75: =AM28 -> 5463398.2 | E75: =AM32 -> 6068321.8 | F75: =AM35 -> 0
C76: =AN23 -> 36 | D76: =AN28 -> 5920462.3 | E76: =AN32 -> 6525385.9 | F76: =AN35 -> 0
C79: Экономический расчёт условно оплачивает труд при разработке; кассовый отражает согласованную отсрочку и последующее погашение. Это разные основания оценки.
C81: DPP — первая точка перехода накопленного DCF через ноль с линейной интерполяцией внутри месяца. Если пересечения нет, срок не достигнут.
C83: Денежные потоки конца месяца. IRR может не иметь решения или быть неоднозначной при нескольких сменах знака.

Sheet Конкуренты
C2: Конкуренты
C4: Сценарий: | D4: ='Исходные данные'!$G$5 -> Базовый
C6: Ценовое сравнение | D6: Cyberbara | E6: Brand Analytics | F6: СКАН: ценовой прокси
C7: Подписка, руб./мес. | D7: ='Исходные данные'!$D$33 -> 20000 | E7: ='Исходные данные'!$D$24 -> 35000 | F7: =AVERAGE('Исходные данные'!$D$24,'Исходные данные'!$D$25*'Исходные данные'!$D$23) -> 39955
C8: Внедрение / обучение, руб. | D8: =SUM('CAPEX OPEX TCO'!D32:D34) -> 60000 | E8: 10000 | F8: 10000
C9: Внутреннее администрирование, руб./мес. | D9: ='CAPEX OPEX TCO'!D36 -> 2000 | E9: 2000 | F9: 2000
C10: TCO клиента за период | D10: =D8+(D7+D9)*'Исходные данные'!$D$21 -> 852000 | E10: =E8+(E7+E9)*'Исходные данные'!$D$21 -> 1342000 | F10: =F8+(F7+F9)*'Исходные данные'!$D$21 -> 1520380
C11: Экономический индекс | D11: =MIN($D$10:$F$10)/D10 -> 1 | E11: =MIN($D$10:$F$10)/E10 -> 0.63487332 | F11: =MIN($D$10:$F$10)/F10 -> 0.56038622
C14: Критерий | D14: Вес | E14: Cyberbara: план | F14: Brand Analytics | G14: СКАН: оценка
C15: Источники и полнота охвата | D15: 0.25 | E15: 2 | F15: 5 | G15: 4
C16: Темы и тональность | D16: 0.25 | E16: 3 | F16: 5 | G16: 4
C17: Уведомления и отчёты | D17: 0.25 | E17: 3 | F17: 5 | G17: 5
C18: Проверяемость и настройка | D18: 0.25 | E18: 4 | F18: 4 | G18: 4
C19: Понятность интерфейса | D19: 0.5 | E19: 3 | F19: 4 | G19: 4
C20: Гибкость настройки | D20: 0.5 | E20: 4 | F20: 4 | G20: 4
C21: Поддержка и документация | D21: 0.5 | E21: 2 | F21: 5 | G21: 5
C22: Условия подключения | D22: 0.5 | E22: 3 | F22: 4 | G22: 4
C25: Группа | D25: Вес | E25: Cyberbara | F25: Brand Analytics | G25: СКАН: оценка
C26: Функциональность | D26: 0.4 | E26: =SUMPRODUCT($D$15:$D$18,E15:E18)/5 -> 0.6 | F26: =SUMPRODUCT($D$15:$D$18,F15:F18)/5 -> 0.95 | G26: =SUMPRODUCT($D$15:$D$18,G15:G18)/5 -> 0.85
C27: Удобство | D27: 0.15 | E27: =SUMPRODUCT($D$19:$D$20,E19:E20)/5 -> 0.7 | F27: =SUMPRODUCT($D$19:$D$20,F19:F20)/5 -> 0.8 | G27: =SUMPRODUCT($D$19:$D$20,G19:G20)/5 -> 0.8
C28: Организационные условия | D28: 0.15 | E28: =SUMPRODUCT($D$21:$D$22,E21:E22)/5 -> 0.5 | F28: =SUMPRODUCT($D$21:$D$22,F21:F22)/5 -> 0.9 | G28: =SUMPRODUCT($D$21:$D$22,G21:G22)/5 -> 0.9
C29: Стоимость владения | D29: 0.3 | E29: =D11 -> 1 | F29: =E11 -> 0.63487332 | G29: =F11 -> 0.56038622
C30: Итоговый индекс | E30: =SUMPRODUCT($D$26:$D$29,E26:E29) -> 0.72 | F30: =SUMPRODUCT($D$26:$D$29,F26:F29) -> 0.825462 | G30: =SUMPRODUCT($D$26:$D$29,G26:G29) -> 0.76311587
C33: Цена СКАН — НЕ тариф поставщика: среднее Brand Analytics 35 000 ₽ и YouScan 499 USD × условный курс. Это разрешённый пользователем рыночный прокси.
C35: Два ориентира не образуют репрезентативную среднюю рынка. Отличаются регионы, охват, лимиты, сроки оплаты и функции; сравнение требует коммерческих предложений.
C37: Оценки 1–5 — учебная сравнительная гипотеза. Cyberbara оценена по планируемым функциям MVP, конкуренты — по публичным описаниям, не по одинаковым тестам.
C39: Внедрение/обучение и администрирование аналогов — отдельные учебные допущения. Публичные тарифы не индексируются на горизонте сравнения.
C41: По шкале 1–5 блоки нормированы на 5, веса групп дают 100%. Индекс цены = минимальное TCO / TCO продукта; формула согласована с примером пособия.
C43: Приоритеты Cyberbara: подтвердить охват источников, качество классификации, UX, документацию и сопровождение; ценовое преимущество пока условное.

Sheet Проверки
C2: Проверки
C4: Сценарий: | D4: ='Исходные данные'!$G$5 -> Базовый
C6: Проверка | D6: Разница / число | E6: Ожидается | F6: По модели | G6: Контроль / граница | I6: Результат | J6: Сопоставляемые показатели и источники
C7: Начислено = выплачено + остаток | D7: =SUM('Продажи и потоки'!D34:AN34)-SUM('Продажи и потоки'!D39:AN39)-'Продажи и потоки'!AN40 -> 4.6566129e-10 | E7: 0 | F7: =SUM('Продажи и потоки'!D34:AN34) -> 2307097.2 | G7: =SUM('Продажи и потоки'!D39:AN39)+'Продажи и потоки'!AN40 -> 2307097.2 | I7: =IF(AND(ISNUMBER(D7),ISNUMBER(E7),ISNUMBER(F7),ISNUMBER(G7)),IF(ABS(D7-E7)<=0.01,"Согласовано","Расхождение"),"Нет числовых данных") -> Согласовано | J7: Начислено; выплачено + остаток. «Продажи и потоки», строки 34, 39, 40.
C8: Стоимость MVP = деньги + труд/взносы + износ | D8: ='CAPEX OPEX TCO'!D11-SUM('CAPEX OPEX TCO'!D12:D14) -> 0 | E8: 0 | F8: ='CAPEX OPEX TCO'!D11 -> 2424769.2 | G8: =SUM('CAPEX OPEX TCO'!D12:D14) -> 2424769.2 | I8: =IF(AND(ISNUMBER(D8),ISNUMBER(E8),ISNUMBER(F8),ISNUMBER(G8)),IF(ABS(D8-E8)<=0.01,"Согласовано","Расхождение"),"Нет числовых данных") -> Согласовано | J8: Полная стоимость и сумма денег, отложенной оценки труда с взносами и амортизации за разработку.
C9: Экономический итог = касса − остаток труда | D9: ='Продажи и потоки'!AN44-'Продажи и потоки'!AN42+'Продажи и потоки'!AN40 -> -1.8626451e-09 | E9: 0 | F9: ='Продажи и потоки'!AN44 -> 11132660 | G9: ='Продажи и потоки'!AN42-'Продажи и потоки'!AN40 -> 11132660 | I9: =IF(AND(ISNUMBER(D9),ISNUMBER(E9),ISNUMBER(F9),ISNUMBER(G9)),IF(ABS(D9-E9)<=0.01,"Согласовано","Расхождение"),"Нет числовых данных") -> Согласовано | J9: Экономический итог; касса − остаток. «Продажи и потоки», AN44, AN42, AN40.
C10: Нормировка весов конкурентов | D10: =SUM(Конкуренты!D26:D29)-1 -> 0 | E10: 0 | F10: =SUM(Конкуренты!D26:D29) -> 1 | G10: =1 -> 1 | I10: =IF(AND(ISNUMBER(D10),ISNUMBER(E10),ISNUMBER(F10),ISNUMBER(G10)),IF(ABS(D10-E10)<=0.01,"Согласовано","Расхождение"),"Нет числовых данных") -> Согласовано | J10: Сумма весов; норматив 1. «Конкуренты», D26:D29.
C11: Последний накопленный DCF = NPV | D11: ='NPV IRR окупаемость'!AN28-'NPV IRR окупаемость'!D10 -> 0 | E11: 0 | F11: ='NPV IRR окупаемость'!AN28 -> 5920462.3 | G11: ='NPV IRR окупаемость'!D10 -> 5920462.3 | I11: =IF(AND(ISNUMBER(D11),ISNUMBER(E11),ISNUMBER(F11),ISNUMBER(G11)),IF(ABS(D11-E11)<=0.01,"Согласовано","Расхождение"),"Нет числовых данных") -> Согласовано | J11: Накопленный DCF; NPV. «NPV IRR окупаемость», AN28 и D10.
C12: TCO клиента согласован с конкурентами | D12: ='CAPEX OPEX TCO'!D38-Конкуренты!D10 -> 0 | E12: 0 | F12: ='CAPEX OPEX TCO'!D38 -> 852000 | G12: =Конкуренты!D10 -> 852000 | I12: =IF(AND(ISNUMBER(D12),ISNUMBER(E12),ISNUMBER(F12),ISNUMBER(G12)),IF(ABS(D12-E12)<=0.01,"Согласовано","Расхождение"),"Нет числовых данных") -> Согласовано | J12: TCO клиента из «CAPEX OPEX TCO» D38 и «Конкуренты» D10.
C13: Отрицательные остатки компенсации | D13: =COUNTIFS('Продажи и потоки'!D40:AN40,"<-0.01") -> 0 | E13: 0 | F13: =MIN('Продажи и потоки'!D40:AN40) -> 0 | G13: =0 -> 0 | I13: =IF(AND(ISNUMBER(D13),ISNUMBER(E13),ISNUMBER(F13),ISNUMBER(G13)),IF(ABS(D13-E13)<=0.01,"Согласовано","Расхождение"),"Нет числовых данных") -> Согласовано | J13: Минимальный остаток; нижняя граница 0. Ошибка — число отрицательных остатков.
C14: Компенсация сверх разрешённой доли | D14: =SUM(D25:AN25) -> 0 | E14: 0 | F14: =SUM('Продажи и потоки'!D39:AN39) -> 2307097.2 | G14: =SUM('Продажи и потоки'!D38:AN38) -> 6719878.8 | I14: =IF(AND(ISNUMBER(D14),ISNUMBER(E14),ISNUMBER(F14),ISNUMBER(G14)),IF(ABS(D14-E14)<=0.01,"Согласовано","Расхождение"),"Нет числовых данных") -> Согласовано | J14: Выплачено; суммарный лимит. Ошибка — сумма помесячных превышений.
C15: Клиентский баланс | D15: =SUM(D26:AN26) -> 0 | E15: 0 | F15: ='Продажи и потоки'!AN16 -> 75.382181 | G15: =SUM('Продажи и потоки'!D14:AN14)-SUM('Продажи и потоки'!D15:AN15) -> 75.382181 | I15: =IF(AND(ISNUMBER(D15),ISNUMBER(E15),ISNUMBER(F15),ISNUMBER(G15)),IF(ABS(D15-E15)<=0.01,"Согласовано","Расхождение"),"Нет числовых данных") -> Согласовано | J15: Клиенты на конец; новые − ушедшие. Ошибка — сумма модулей месячных разниц.
C16: Дефицит при выплатах команде | D16: =SUM(D27:AN27) -> 0 | E16: 0 | F16: =SUM(D27:AN27) -> 0 | G16: =0 -> 0 | I16: =IF(AND(ISNUMBER(D16),ISNUMBER(E16),ISNUMBER(F16),ISNUMBER(G16)),IF(ABS(D16-E16)<=0.01,"Согласовано","Расхождение"),"Нет числовых данных") -> Согласовано | J16: Число месяцев выплат при дефиците; ожидается 0. «Продажи и потоки», строки 39, 42.
C19: Ноль в «Разница / число» означает, что проверка сходится. Суммы из модели показаны справа. В строках 13–16 проверяются границы и число нарушений.
C24: Месяц | D24: ='Продажи и потоки'!D6 -> 0 | E24: ='Продажи и потоки'!E6 -> 1 | F24: ='Продажи и потоки'!F6 -> 2 | G24: ='Продажи и потоки'!G6 -> 3 | H24: ='Продажи и потоки'!H6 -> 4 | I24: ='Продажи и потоки'!I6 -> 5 | J24: ='Продажи и потоки'!J6 -> 6 | K24: ='Продажи и потоки'!K6 -> 7 | ... AN24: ='Продажи и потоки'!AN6 -> 36
C25: Превышение лимита выплат, руб. | D25: =MAX(0,'Продажи и потоки'!D39-'Продажи и потоки'!D38) -> 0 | E25: =MAX(0,'Продажи и потоки'!E39-'Продажи и потоки'!E38) -> 0 | F25: =MAX(0,'Продажи и потоки'!F39-'Продажи и потоки'!F38) -> 0 | G25: =MAX(0,'Продажи и потоки'!G39-'Продажи и потоки'!G38) -> 0 | H25: =MAX(0,'Продажи и потоки'!H39-'Продажи и потоки'!H38) -> 0 | I25: =MAX(0,'Продажи и потоки'!I39-'Продажи и потоки'!I38) -> 0 | J25: =MAX(0,'Продажи и потоки'!J39-'Продажи и потоки'!J38) -> 0 | K25: =MAX(0,'Продажи и потоки'!K39-'Продажи и потоки'!K38) -> 0 | ... AN25: =MAX(0,'Продажи и потоки'!AN39-'Продажи и потоки'!AN38) -> 0
C26: Ошибка баланса клиентов, модуль | D26: =ABS('Продажи и потоки'!D13+'Продажи и потоки'!D14-'Продажи и потоки'!D15-'Продажи и потоки'!D16) -> 0 | E26: =ABS('Продажи и потоки'!E13+'Продажи и потоки'!E14-'Продажи и потоки'!E15-'Продажи и потоки'!E16) -> 0 | F26: =ABS('Продажи и потоки'!F13+'Продажи и потоки'!F14-'Продажи и потоки'!F15-'Продажи и потоки'!F16) -> 0 | G26: =ABS('Продажи и потоки'!G13+'Продажи и потоки'!G14-'Продажи и потоки'!G15-'Продажи и потоки'!G16) -> 0 | H26: =ABS('Продажи и потоки'!H13+'Продажи и потоки'!H14-'Продажи и потоки'!H15-'Продажи и потоки'!H16) -> 0 | I26: =ABS('Продажи и потоки'!I13+'Продажи и потоки'!I14-'Продажи и потоки'!I15-'Продажи и потоки'!I16) -> 0 | J26: =ABS('Продажи и потоки'!J13+'Продажи и потоки'!J14-'Продажи и потоки'!J15-'Продажи и потоки'!J16) -> 0 | K26: =ABS('Продажи и потоки'!K13+'Продажи и потоки'!K14-'Продажи и потоки'!K15-'Продажи и потоки'!K16) -> 0 | ... AN26: =ABS('Продажи и потоки'!AN13+'Продажи и потоки'!AN14-'Продажи и потоки'!AN15-'Продажи и потоки'!AN16) -> 0
C27: Выплаты при дефиците: число месяцев | D27: =IF(AND('Продажи и потоки'!D39>0.01,'Продажи и потоки'!D42<-0.01),1,0) -> 0 | E27: =IF(AND('Продажи и потоки'!E39>0.01,'Продажи и потоки'!E42<-0.01),1,0) -> 0 | F27: =IF(AND('Продажи и потоки'!F39>0.01,'Продажи и потоки'!F42<-0.01),1,0) -> 0 | G27: =IF(AND('Продажи и потоки'!G39>0.01,'Продажи и потоки'!G42<-0.01),1,0) -> 0 | H27: =IF(AND('Продажи и потоки'!H39>0.01,'Продажи и потоки'!H42<-0.01),1,0) -> 0 | I27: =IF(AND('Продажи и потоки'!I39>0.01,'Продажи и потоки'!I42<-0.01),1,0) -> 0 | J27: =IF(AND('Продажи и потоки'!J39>0.01,'Продажи и потоки'!J42<-0.01),1,0) -> 0 | K27: =IF(AND('Продажи и потоки'!K39>0.01,'Продажи и потоки'!K42<-0.01),1,0) -> 0 | ... AN27: =IF(AND('Продажи и потоки'!AN39>0.01,'Продажи и потоки'!AN42<-0.01),1,0) -> 0
C30: Пул = ФОТ + обязательные взносы | D30: =F30-G30 -> 0 | E30: 0 | F30: ='COCOMO и разработка'!G43 -> 2307097.2 | G30: =SUM('COCOMO и разработка'!G41:G42) -> 2307097.2 | I30: =IF(ABS(D30)<=0.01,"Согласовано","Расхождение") -> Согласовано | J30: Независимое сопоставление расчёта и его основания.
C31: Амортизация за горизонт совпадает | D31: =F31-G31 -> 0 | E31: 0 | F31: =SUM('Продажи и потоки'!D60:AN60) -> 249048 | G31: ='Оборудование и амортизация'!F30 -> 249048 | I31: =IF(ABS(D31)<=0.01,"Согласовано","Расхождение") -> Согласовано | J31: Независимое сопоставление расчёта и его основания.
C32: Труд четырёх участников = труд ролей | D32: =F32-G32 -> 0 | E32: 0 | F32: ='COCOMO и разработка'!E69 -> 10.561772 | G32: ='COCOMO и разработка'!E41 -> 10.561772 | I32: =IF(ABS(D32)<=0.01,"Согласовано","Расхождение") -> Согласовано | J32: Независимое сопоставление расчёта и его основания.
C33: Ресурсные затраты за горизонт | D33: =F33-G33 -> 0 | E33: 0 | F33: =SUM('Продажи и потоки'!D61:AN61) -> 16041850 | G33: ='CAPEX OPEX TCO'!D27 -> 16041850 | I33: =IF(ABS(D33)<=0.01,"Согласовано","Расхождение") -> Согласовано | J33: Независимое сопоставление расчёта и его основания.
C34: Состав команды = 4 участника | D34: =F34-G34 -> 0 | E34: 0 | F34: ='Исходные данные'!D11 -> 4 | G34: =4 -> 4 | I34: =IF(ABS(D34)<=0.01,"Согласовано","Расхождение") -> Согласовано | J34: Независимое сопоставление расчёта и его основания.
